Workbook

Sheet Pool Buy Scenarios
A1: PN | B1: Group: A- Inhouse Cap B- OEMs C- Others | C1: IP1- Standalone | D1: Standalone IP1 Qty | E1: IP3- Adj Current Fleet only | F1: IP3 Qty | G1: IP2 - Current Fleet+ Skymark | H1: IP2 Qty | I1: Adjusted Total Avail Pool based on Pool Std | J1: IP2 less Inhouse Pool | K1: IP Qty (Difference Model), considering inhouse pool | L1: 2026 MLP w Tariff (USD) | M1: Manual Top-up for zero stock items | N1: Pool Buy Qty | O1: Pool Buy (USD)
A2: AR4709-13 | B2: =VLOOKUP(A2, partCapability!$B$1:$Q$8000, 16, FALSE) -> Grp C (Others) | C2: =IFERROR(VLOOKUP(A2, partNumbers!$A$1:$E$8000, 5, FALSE), 0) -> 60 | D2: 1 | E2: =IFERROR(VLOOKUP(A2, currentMbhFleet!$S$1:$AO$8000, 17, FALSE), 0) -> 66 | F2: 1 | G2: =C2+E2 -> 126 | H2: 2 | I2: 0 | J2: =H2-I2 -> 2 | K2: =IF(J2<0, 0, IF(E2>0, H2-F2, MAX(0, D2-I2))) -> 1 | L2: =IFERROR(VLOOKUP(A2, partNumbers!$A$1:$Z$5000, 7, FALSE), 0) -> 19380 | M2: 0 | N2: =K2+M2 -> 1 | O2: =N2*L2 -> 19380
A3: AR4714-11 | B3: =VLOOKUP(A3, partCapability!$B$1:$Q$8000, 16, FALSE) -> Grp C (Others) | C3: =IFERROR(VLOOKUP(A3, partNumbers!$A$1:$E$8000, 5, FALSE), 0) -> 60 | D3: 1 | E3: =IFERROR(VLOOKUP(A3, currentMbhFleet!$S$1:$AO$8000, 17, FALSE), 0) -> 105 | F3: 2 | G3: =C3+E3 -> 165 | H3: 2 | I3: 7 | J3: =H3-I3 -> -5 | K3: =IF(J3<0, 0, IF(E3>0, H3-F3, MAX(0, D3-I3))) -> 0 | L3: =IFERROR(VLOOKUP(A3, partNumbers!$A$1:$Z$5000, 7, FALSE), 0) -> 6210 | M3: 0 | N3: =K3+M3 -> 0 | O3: =N3*L3 -> 0
A4: AR4714-7 | B4: =VLOOKUP(A4, partCapability!$B$1:$Q$8000, 16, FALSE) -> Grp C (Others) | C4: =IFERROR(VLOOKUP(A4, partNumbers!$A$1:$E$8000, 5, FALSE), 0) -> 60 | D4: 1 | E4: =IFERROR(VLOOKUP(A4, currentMbhFleet!$S$1:$AO$8000, 17, FALSE), 0) -> 105 | F4: 2 | G4: =C4+E4 -> 165 | H4: 3 | I4: 6 | J4: =H4-I4 -> -3 | K4: =IF(J4<0, 0, IF(E4>0, H4-F4, MAX(0, D4-I4))) -> 0 | L4: =IFERROR(VLOOKUP(A4, partNumbers!$A$1:$Z$5000, 7, FALSE), 0) -> 6100 | M4: 0 | N4: =K4+M4 -> 0 | O4: =N4*L4 -> 0
A5: AR90122-5D605 | B5: =VLOOKUP(A5, partCapability!$B$1:$Q$8000, 16, FALSE) -> Grp C (Others) | C5: =IFERROR(VLOOKUP(A5, partNumbers!$A$1:$E$8000, 5, FALSE), 0) -> 60 | D5: 3 | E5: =IFERROR(VLOOKUP(A5, currentMbhFleet!$S$1:$AO$8000, 17, FALSE), 0) -> 0 | F5: 0 | G5: =C5+E5 -> 60 | H5: 3 | I5: 0 | J5: =H5-I5 -> 3 | K5: =IF(J5<0, 0, IF(E5>0, H5-F5, MAX(0, D5-I5))) -> 3 | L5: =IFERROR(VLOOKUP(A5, partNumbers!$A$1:$Z$5000, 7, FALSE), 0) -> 117680 | M5: 0 | N5: =K5+M5 -> 3 | O5: =N5*L5 -> 353040
A6: Z014H010035C | B6: =VLOOKUP(A6, partCapability!$B$1:$Q$8000, 16, FALSE) -> Grp C (Others) | C6: =IFERROR(VLOOKUP(A6, partNumbers!$A$1:$E$8000, 5, FALSE), 0) -> 60 | D6: 13 | E6: =IFERROR(VLOOKUP(A6, currentMbhFleet!$S$1:$AO$8000, 17, FALSE), 0) -> 66 | F6: 14 | G6: =C6+E6 -> 126 | H6: 24 | I6: 3 | J6: =H6-I6 -> 21 | K6: =IF(J6<0, 0, IF(E6>0, H6-F6, MAX(0, D6-I6))) -> 10 | L6: =IFERROR(VLOOKUP(A6, partNumbers!$A$1:$Z$5000, 7, FALSE), 0) -> 140502 | M6: 0 | N6: =K6+M6 -> 10 | O6: =N6*L6 -> 1405020
A7: Z043H0101110 | B7: =VLOOKUP(A7, partCapability!$B$1:$Q$8000, 16, FALSE) -> Grp C (Others) | C7: =IFERROR(VLOOKUP(A7, partNumbers!$A$1:$E$8000, 5, FALSE), 0) -> 60 | D7: 9 | E7: =IFERROR(VLOOKUP(A7, currentMbhFleet!$S$1:$AO$8000, 17, FALSE), 0) -> 0 | F7: 0 | G7: =C7+E7 -> 60 | H7: 9 | I7: 4 | J7: =H7-I7 -> 5 | K7: =IF(J7<0, 0, IF(E7>0, H7-F7, MAX(0, D7-I7))) -> 5 | L7: =IFERROR(VLOOKUP(A7, partNumbers!$A$1:$Z$5000, 7, FALSE), 0) -> 7441 | M7: 0 | N7: =K7+M7 -> 5 | O7: =N7*L7 -> 37205
A8: Z111H0040131 | B8: =VLOOKUP(A8, partCapability!$B$1:$Q$8000, 16, FALSE) -> Grp C (Others) | C8: =IFERROR(VLOOKUP(A8, partNumbers!$A$1:$E$8000, 5, FALSE), 0) -> 60 | D8: 12 | E8: =IFERROR(VLOOKUP(A8, currentMbhFleet!$S$1:$AO$8000, 17, FALSE), 0) -> 0 | F8: 0 | G8: =C8+E8 -> 60 | H8: 12 | I8: 0 | J8: =H8-I8 -> 12 | K8: =IF(J8<0, 0, IF(E8>0, H8-F8, MAX(0, D8-I8))) -> 12 | L8: =IFERROR(VLOOKUP(A8, partNumbers!$A$1:$Z$5000, 7, FALSE), 0) -> 8029 | M8: 0 | N8: =K8+M8 -> 12 | O8: =N8*L8 -> 96348
A9: Z145HA452120 | B9: =VLOOKUP(A9, partCapability!$B$1:$Q$8000, 16, FALSE) -> Grp C (Others) | C9: =IFERROR(VLOOKUP(A9, partNumbers!$A$1:$E$8000, 5, FALSE), 0) -> 60 | D9: 5 | E9: =IFERROR(VLOOKUP(A9, currentMbhFleet!$S$1:$AO$8000, 17, FALSE), 0) -> 0 | F9: 0 | G9: =C9+E9 -> 60 | H9: 6 | I9: 0 | J9: =H9-I9 -> 6 | K9: =IF(J9<0, 0, IF(E9>0, H9-F9, MAX(0, D9-I9))) -> 5 | L9: =IFERROR(VLOOKUP(A9, partNumbers!$A$1:$Z$5000, 7, FALSE), 0) -> 76480 | M9: 0 | N9: =K9+M9 -> 5 | O9: =N9*L9 -> 382400
A10: Z212H0001110 | B10: =VLOOKUP(A10, partCapability!$B$1:$Q$8000, 16, FALSE) -> Grp C (Others) | C10: =IFERROR(VLOOKUP(A10, partNumbers!$A$1:$E$8000, 5, FALSE), 0) -> 60 | D10: 13 | E10: =IFERROR(VLOOKUP(A10, currentMbhFleet!$S$1:$AO$8000, 17, FALSE), 0) -> 89 | F10: 19 | G10: =C10+E10 -> 149 | H10: 30 | I10: 3 | J10: =H10-I10 -> 27 | K10: =IF(J10<0, 0, IF(E10>0, H10-F10, MAX(0, D10-I10))) -> 11 | L10: =IFERROR(VLOOKUP(A10, partNumbers!$A$1:$Z$5000, 7, FALSE), 0) -> 2968 | M10: 0 | N10: =K10+M10 -> 11 | O10: =N10*L10 -> 32648
A11: Z212H0009110 | B11: =VLOOKUP(A11, partCapability!$B$1:$Q$8000, 16, FALSE) -> Grp C (Others) | C11: =IFERROR(VLOOKUP(A11, partNumbers!$A$1:$E$8000, 5, FALSE), 0) -> 60 | D11: 2 | E11: =IFERROR(VLOOKUP(A11, currentMbhFleet!$S$1:$AO$8000, 17, FALSE), 0) -> 0 | F11: 0 | G11: =C11+E11 -> 60 | H11: 2 | I11: 0 | J11: =H11-I11 -> 2 | K11: =IF(J11<0, 0, IF(E11>0, H11-F11, MAX(0, D11-I11))) -> 2 | L11: =IFERROR(VLOOKUP(A11, partNumbers!$A$1:$Z$5000, 7, FALSE), 0) -> 4550 | M11: 0 | N11: =K11+M11 -> 2 | O11: =N11*L11 -> 9100
A12: Z213H0101111 | B12: =VLOOKUP(A12, partCapability!$B$1:$Q$8000, 16, FALSE) -> Grp C (Others) | C12: =IFERROR(VLOOKUP(A12, partNumbers!$A$1:$E$8000, 5, FALSE), 0) -> 60 | D12: 7 | E12: =IFERROR(VLOOKUP(A12, currentMbhFleet!$S$1:$AO$8000, 17, FALSE), 0) -> 0 | F12: 0 | G12: =C12+E12 -> 60 | H12: 7 | I12: 0 | J12: =H12-I12 -> 7 | K12: =IF(J12<0, 0, IF(E12>0, H12-F12, MAX(0, D12-I12))) -> 7 | L12: =IFERROR(VLOOKUP(A12, partNumbers!$A$1:$Z$5000, 7, FALSE), 0) -> 8990 | M12: 0 | N12: =K12+M12 -> 7 | O12: =N12*L12 -> 62930
A13: Z233H0000110 | B13: =VLOOKUP(A13, partCapability!$B$1:$Q$8000, 16, FALSE) -> Grp C (Others) | C13: =IFERROR(VLOOKUP(A13, partNumbers!$A$1:$E$8000, 5, FALSE), 0) -> 60 | D13: 11 | E13: =IFERROR(VLOOKUP(A13, currentMbhFleet!$S$1:$AO$8000, 17, FALSE), 0) -> 66 | F13: 12 | G13: =C13+E13 -> 126 | H13: 21 | I13: 1 | J13: =H13-I13 -> 20 | K13: =IF(J13<0, 0, IF(E13>0, H13-F13, MAX(0, D13-I13))) -> 9 | L13: =IFERROR(VLOOKUP(A13, partNumbers!$A$1:$Z$5000, 7, FALSE), 0) -> 1124 | M13: 0 | N13: =K13+M13 -> 9 | O13: =N13*L13 -> 10116
... A282: RCF6717 | B282: =VLOOKUP(A282, partCapability!$B$1:$Q$8000, 16, FALSE) -> Grp A (CRO) | C282: =IFERROR(VLOOKUP(A282, partNumbers!$A$1:$E$8000, 5, FALSE), 0) -> 60 | D282: 6 | E282: =IFERROR(VLOOKUP(A282, currentMbhFleet!$S$1:$AO$8000, 17, FALSE), 0) -> 93 | F282: 8 | G282: =C282+E282 -> 153 | H282: 11 | I282: 2 | J282: =H282-I282 -> 9 | K282: =IF(J282<0, 0, IF(E282>0, H282-F282, MAX(0, D282-I282))) -> 3 | L282: =IFERROR(VLOOKUP(A282, partNumbers!$A$1:$Z$5000, 7, FALSE), 0) -> 9475 | M282: 0 | N282: =K282+M282 -> 3 | O282: =N282*L282 -> 28425

Sheet partNumbers
A1: PN | B1: Annual FH | C1: RRI | D1: Buy Price (USD) | E1: Aircraft Count | F1: FAM Class | G1: 2026 MLP w Tariff (USD)
A2: AR4709-13 | B2: 4000 | C2: 0 | D2: 19380 | E2: 60 | F2: STEAS00138 | G2: 19380
A3: AR4714-11 | B3: 4000 | C3: 0 | D3: 5877.3333 | E3: 60 | F3: STEAS00454 | G3: 6210
A4: AR4714-7 | B4: 4000 | C4: 0 | D4: 6100 | E4: 60 | F4: STEAS00453 | G4: 6100
A5: AR90122-5D605 | B5: 4000 | C5: 0 | D5: 117680 | E5: 60 | F5: STEAS00218 | G5: 117680
A6: Z014H010035C | B6: 4000 | C6: 0 | D6: 140502.45 | E6: 60 | F6: STEAS00179 | G6: 140502
A7: Z043H0101110 | B7: 4000 | C7: 0 | D7: 7441.22 | E7: 60 | F7: STEAS00178 | G7: 7441
A8: Z111H0040131 | B8: 4000 | C8: 0 | D8: 8029.07 | E8: 60 | F8: STEAS00052 | G8: 8029
A9: Z145HA452120 | B9: 4000 | C9: 0 | D9: 76480 | E9: 60 | F9: STEAS00216 | G9: 76480
A10: Z212H0001110 | B10: 4000 | C10: 0 | D10: 2968.04 | E10: 60 | F10: STEAS00127 | G10: 2968
A11: Z212H0009110 | B11: 4000 | C11: 0 | D11: 4550 | E11: 60 | F11: A320-FAM027 | G11: 4550
A12: Z213H0101111 | B12: 4000 | C12: 0 | D12: 8990 | E12: 60 | F12: A320-FAM028 | G12: 8990
A13: Z233H0000110 | B13: 4000 | C13: 0 | D13: 1124.21 | E13: 60 | F13: STEAS00085 | G13: 1124
... A282: RCF6717 | B282: 4000 | C282: 0 | D282: 9474.51 | E282: 60 | F282: STEAS00382 | G282: 9475

Sheet partCapability
A1: No | B1: PNR | C1: OEM | D1: ATA | E1: ADT | F1: SPC | G1: ESS | H1: MTBUR | I1: QPA | J1: MLP | K1: MLP Source | L1: Buy Price | M1: Buy Price Source | N1: Buy price/MLP % | O1: Include/Exclude from Repair Run | P1: Include/Exclude from IP Run | Q1: Grp A,B,C | R1: SPT | S1: To support MBH? (Bo Rong) | T1: Remarks (Bo Rong) | U1: FAM Class | V1: FAM Class Count | W1: Can you provide repair suport for this part? (YES/NO) | X1: Can you repair it internally within your own MRO, or external subcontracor? | Y1: MRO Cage Code | Z1: MRO Location
A2: 155 | B2: 25225-01 | C2: NORD-MICRO GMBH & CO OHG | D2: 21 | E2: HEATER-DUCT | F2: 2 | G2: 3 | H2: 48000 | I2: 2 | J2: 19030 | K2: Airbus web 23/3/26 | L2: 19030 | M2: Airbus web 23/3/26 | N2: 1 | O2: Include | P2: Include | Q2: Grp C (Others) | R2: 30 | U2: A320-FAM001 | V2: 1
A3: 158 | B3: 405005-00000 | C3: THALES AEROSPACE COMMUNICATIONS | D3: 23 | E3: ANTENNA-LOW GAIN | F3: 6 | G3: 2 | H3: 99750 | I3: 1 | J3: 72640 | K3: Airbus web 23/3/26 | L3: 72640 | M3: Airbus web 23/3/26 | N3: 1 | O3: Exclude | P3: Exclude | S3: No | T3: Reference to JAL experience | U3: A320-FAM002 | V3: 1
A4: 276 | B4: Z934H0503110 | C4: KID SYSTEME GMBH | D4: 23 | E4: CAMERA-CDSS | F4: 2 | G4: 3 | H4: 86400 | I4: 1 | J4: 7780 | K4: Airbus web 23/3/26 | L4: 7780 | M4: Airbus web 23/3/26 | N4: 1 | O4: Include | P4: Include | Q4: Grp C (Others) | R4: 30 | U4: A320-FAM003 | V4: 1
A5: 307 | B5: Z318H078031E | C5: AIRBUS OPERATIONS GMBH | D5: 23 | E5: PANEL-INFORMATION | F5: 2 | G5: 3 | H5: 90000 | I5: 1 | J5: 4770 | K5: Airbus web 23/3/26 | L5: 4770 | M5: Airbus web 23/3/26 | N5: 1 | O5: Include | P5: Include | Q5: Grp C (Others) | R5: 30 | U5: A320-FAM004 | V5: 1
A6: 92 | B6: Z318H015013E | C6: AIRBUS OPERATIONS GMBH | D6: 23 | E6: PSU-PASSENGER SERVICE UNIT | F6: 2 | G6: 3 | H6: 90000 | I6: 10 | J6: 7527.7 | K6: Airbus C9072 Catalogue 2026 | L6: 7527.7 | M6: Airbus C9072 Catalogue 2026 | N6: 1 | O6: Include | P6: Include | Q6: Grp C (Others) | R6: 30 | U6: A320-FAM005 | V6: 1
A7: 52 | B7: Z318H017013E | C7: AIRBUS OPERATIONS GMBH | D7: 23 | E7: PSU-PASSENGER SERVICE UNIT | F7: 2 | G7: 3 | H7: 90000 | I7: 36 | J7: 7527.7 | K7: Airbus C9072 Catalogue 2026 | L7: 7527.7 | M7: Airbus C9072 Catalogue 2026 | N7: 1 | O7: Include | P7: Include | Q7: Grp C (Others) | R7: 30 | U7: A320-FAM006 | V7: 1
A8: 83 | B8: Z318H037023E | C8: AIRBUS OPERATIONS GMBH | D8: 23 | E8: PSU-PASSENGER SERVICE UNIT | F8: 2 | G8: 3 | H8: 90000 | I8: 22 | J8: 9610 | K8: Airbus web 23/3/26 | L8: 9610 | M8: Airbus web 23/3/26 | N8: 1 | O8: Include | P8: Include | Q8: Grp C (Others) | R8: 30 | U8: A320-FAM007 | V8: 1
A9: 49 | B9: RMP4381AA110101 | C9: THALES AEROSPACE COMMUNICATIONS | D9: 23 | E9: RMP-RADIO MANAGEMENT PANEL | F9: 2 | G9: 1 | H9: 23400 | I9: 2 | J9: 52010 | K9: Airbus web 23/3/26 | L9: 52010 | M9: Airbus web 23/3/26 | N9: 1 | O9: Exclude (BTB with Thales) | P9: Include | Q9: Grp B (OEM) | R9: 30 | T9: Thales | U9: A320-FAM008 | V9: 1
A10: 61 | B10: 405045-00001 | C10: THALES AEROSPACE COMMUNICATIONS | D10: 23 | E10: SDU-SATELLITE DATA UNIT | F10: 6 | G10: 2 | H10: 29925 | I10: 1 | J10: 112260 | K10: Airbus web 23/3/26 | L10: 112260 | M10: Airbus web 23/3/26 | N10: 1 | O10: Include | P10: Include | Q10: Grp C (Others) | R10: 30 | U10: A320-FAM009 | V10: 1
A11: 313 | B11: 1J520-10140-000 | C11: DIEHL AEROSPACE GMBH | D11: 25 | E11: CLEDU-CABIN LED UNIT | F11: 2 | G11: 3 | H11: 57600 | I11: 1 | J11: 2020 | K11: Airbus web 23/3/26 | L11: 2020 | M11: Airbus web 23/3/26 | N11: 1 | O11: Exclude | P11: Exclude | S11: No | T11: High BER Rate | U11: A320-FAM010 | V11: 1
A12: 279 | B12: 1J520-10180-000 | C12: DIEHL AEROSPACE GMBH | D12: 25 | E12: CLEDU-CABIN LED UNIT | F12: 2 | G12: 3 | H12: 57600 | I12: 3 | J12: 1520 | K12: Airbus web 23/3/26 | L12: 1520 | M12: Airbus web 23/3/26 | N12: 1 | O12: Exclude | P12: Exclude | S12: No | T12: High BER Rate | U12: A320-FAM011 | V12: 1
A13: 374 | B13: 1J520-10260-000 | C13: DIEHL AEROSPACE GMBH | D13: 25 | E13: CLEDU-CABIN LED UNIT | F13: 2 | G13: 3 | H13: 999999 | I13: 3 | J13: 1520 | K13: Airbus web 23/3/26 | L13: 1520 | M13: Airbus web 23/3/26 | N13: 1 | O13: Exclude | P13: Exclude | S13: No | T13: High BER Rate | U13: A320-FAM012 | V13: 1
A14: 384 | B14: T900200 | C14: SAFRAN CABIN GERMANY GMBH | D14: 25 | E14: COMPACTOR-TRASH | F14: 2 | G14: 3 | H14: 11250 | I14: 1 | J14: 0 | K14: 0 | L14: 0 | M14: 0 | N14: 0 | O14: Exclude | P14: Exclude | S14: No | T14: High Removal | U14: A320-FAM013 | V14: 2
A15: 385 | B15: T900501 | C15: SAFRAN CABIN GERMANY GMBH | D15: 25 | E15: COMPACTOR-TRASH | F15: 2 | G15: 3 | H15: 11250 | I15: 1 | J15: 0 | K15: 0 | L15: 0 | M15: 0 | N15: 0 | O15: Exclude | P15: Exclude | S15: No | T15: High Removal | U15: A320-FAM013 | V15: 2
A16: 329 | B16: 22C15L120700009 | C16: BE AEROSPACE SYSTEMS GMBH | D16: 25 | E16: CONTAINER ASSY-CHEMICAL OXYGEN,TWO MASK | F16: 2 | G16: 2 | H16: 194400 | I16: 3 | J16: 1830 | K16: Airbus web 23/3/26 | L16: 1830 | M16: Airbus web 23/3/26 | N16: 1 | O16: Exclude | P16: Exclude | S16: No | T16: Typically not supported under MBH | U16: A320-FAM014 | V16: 2
A17: 340 | B17: 22C15L150700009 | C17: BE AEROSPACE SYSTEMS GMBH | D17: 25 | E17: CONTAINER ASSY-CHEMICAL OXYGEN,TWO MASK | F17: 2 | G17: 2 | H17: 390000 | I17: 4 | J17: 1830 | K17: Airbus web 23/3/26 | L17: 1830 | M17: Airbus web 23/3/26 | N17: 1 | O17: Exclude | P17: Exclude | S17: No | T17: Typically not supported under MBH | U17: A320-FAM014 | V17: 2
A18: 170 | B18: 25226-01AA | C18: NORD-MICRO GMBH & CO OHG | D18: 21 | E18: CONTROLLER-HEAT | F18: 2 | G18: 2 | H18: 60000 | I18: 2 | J18: 19370 | K18: Airbus web 23/3/26 | L18: 19370 | M18: Airbus web 23/3/26 | N18: 1 | O18: Include | P18: Include | Q18: Grp C (Others) | R18: 30 | U18: A320-FAM016 | V18: 1
A19: 391 | B19: FE459100002 | C19: RATIER-FIGEAC | D19: 27 | E19: RBPU-RUDDER AND BRAKE PEDAL UNIT,CAPT | F19: 2 | G19: 2 | H19: 37800 | I19: 1 | J19: 107810 | K19: Airbus web 23/3/26 | L19: 107810 | M19: Airbus web 23/3/26 | N19: 1 | O19: Include | P19: Include | Q19: Grp C (Others) | R19: 30 | U19: A320-FAM017 | V19: 1
A20: 392 | B20: FE459200002 | C20: RATIER-FIGEAC | D20: 27 | E20: RBPU-RUDDER AND BRAKE PEDAL UNIT,F0 | F20: 2 | G20: 2 | H20: 86400 | I20: 1 | J20: 68100 | K20: Airbus web 23/3/26 | L20: 68100 | M20: Airbus web 23/3/26 | N20: 1 | O20: Include | P20: Include | Q20: Grp C (Others) | R20: 30 | U20: A320-FAM018 | V20: 1
A21: 183 | B21: 812A0001-01 | C21: LIEBHERR-AEROSPACE LINDENBERG | D21: 27 | E21: SERVOVALVE | F21: 2 | G21: 2 | H21: 98336 | I21: 3 | J21: 14990 | K21: Airbus web 23/3/26 | L21: 14990 | M21: Airbus web 23/3/26 | N21: 1 | O21: Exclude (BTB with Liebherr) | P21: Include | Q21: Grp B (OEM) | R21: 30 | T21: Liebherr | U21: A320-FAM019 | V21: 1
A22: 227 | B22: 3863D0000-01 | C22: LIEBHERR-AEROSPACE LINDENBERG | D22: 27 | E22: TRANSDUCER,PRESSURE,FLUID-HYDRAULIC | F22: 2 | G22: 3 | H22: 152000 | I22: 6 | J22: 6130 | K22: Airbus web 23/3/26 | L22: 6130 | M22: Airbus web 23/3/26 | N22: 1 | O22: Exclude (BTB with Liebherr) | P22: Include | Q22: Grp B (OEM) | R22: 30 | T22: Liebherr | U22: A320-FAM020 | V22: 1
A23: 267 | B23: 12M0172 | C23: EATON LIMITED | D23: 28 | E23: FUEL-TRANSFER VALVE | F23: 2 | G23: 2 | H23: 210000 | I23: 2 | J23: 12770 | K23: Airbus web 23/3/26 | L23: 12770 | M23: Airbus web 23/3/26 | N23: 1 | O23: Include | P23: Include | Q23: Grp C (Others) | R23: 30 | U23: A320-FAM021 | V23: 1
A24: 305 | B24: 59127-0101 | C24: SIMMONDS PRECISION PRODUCTS INC | D24: 28 | E24: HARNESS 4S | F24: 6 | G24: 1 | H24: 117345 | I24: 1 | J24: 6230 | K24: Airbus web 23/3/26 | L24: 6230 | M24: Airbus web 23/3/26 | N24: 1 | O24: Include | P24: Include | Q24: Grp C (Others) | R24: 30 | U24: A320-FAM022 | V24: 1
A25: 306 | B25: 59128-0101 | C25: SIMMONDS PRECISION PRODUCTS INC | D25: 28 | E25: HARNESS 5S | F25: 6 | G25: 1 | H25: 117345 | I25: 1 | J25: 6230 | K25: Airbus web 23/3/26 | L25: 6230 | M25: Airbus web 23/3/26 | N25: 1 | O25: Include | P25: Include | Q25: Grp C (Others) | R25: 30 | U25: A320-FAM023 | V25: 1
A26: 343 | B26: 25K0037-1200 | C26: EATON LIMITED | D26: 28 | E26: REFUEL VALVE CANISTER | F26: 2 | G26: 2 | H26: 630882 | I26: 1 | J26: 9470 | K26: Airbus web 23/3/26 | L26: 9470 | M26: Airbus web 23/3/26 | N26: 1 | O26: Include | P26: Include | Q26: Grp C (Others) | R26: 30 | U26: A320-FAM024 | V26: 1
A27: 393 | B27: 12M0172-1100 | C27: EATON LIMITED | D27: 28 | E27: VALVE FUEL, TRANSFER | F27: 2 | G27: 2 | H27: 210000 | I27: 2 | J27: 12770 | K27: Airbus web 24/3/26 12M0172 | L27: 12770 | M27: Airbus web 24/3/26 12M0172 | N27: 1 | O27: Include | P27: Include | Q27: Grp C (Others) | R27: 30 | U27: A320-FAM025 | V27: 1
A28: 277 | B28: 12M0134-1100 | C28: EATON LIMITED | D28: 28 | E28: VALVE-LP FUEL | F28: 2 | G28: 1 | H28: 190391 | I28: 3 | J28: 6460 | K28: Airbus web 23/3/26 | L28: 6460 | M28: Airbus web 23/3/26 | N28: 1 | O28: Include | P28: Include | Q28: Grp C (Others) | R28: 30 | U28: A320-FAM026 | V28: 1
A29: 254 | B29: Z212H0009110 | C29: AIRBUS OPERATIONS GMBH | D29: 30 | E29: CONTROL UNIT | F29: 2 | G29: 3 | H29: 30000 | I29: 1 | J29: 4550 | K29: Airbus web 23/3/26 | L29: 4550 | M29: Airbus web 23/3/26 | N29: 1 | O29: Include | P29: Include | Q29: Grp C (Others) | R29: 30 | U29: A320-FAM027 | V29: 1
A30: 131 | B30: Z213H0101111 | C30: AIRBUS OPERATIONS GMBH | D30: 30 | E30: UNIT-CONTROL | F30: 2 | G30: 3 | H30: 30000 | I30: 4 | J30: 8990 | K30: Airbus web 23/3/26 | L30: 8990 | M30: Airbus web 23/3/26 | N30: 1 | O30: Include | P30: Include | Q30: Grp C (Others) | R30: 30 | U30: A320-FAM028 | V30: 1
A31: 120 | B31: C19628AD | C31: THALES AVS FRANCE SAS | D31: 31 | E31: HCU-HEAD UP COMBINIER UNIT CAPTAIN | F31: 6 | G31: 2 | H31: 86535 | I31: 1 | J31: 107200 | K31: Airbus web 23/3/26 | L31: 107200 | M31: Airbus web 23/3/26 | N31: 1 | O31: Exclude (BTB with Thales) | P31: Include | Q31: Grp B (OEM) | R31: 30 | T31: Thales | U31: A320-FAM029 | V31: 1
A32: 121 | B32: C19643AD | C32: THALES AVS FRANCE SAS | D32: 31 | E32: HCU-HEAD-UP COMBINER UNIT FIRST OFFICER | F32: 6 | G32: 2 | H32: 86535 | I32: 1 | J32: 107200 | K32: Airbus web 23/3/26 | L32: 107200 | M32: Airbus web 23/3/26 | N32: 1 | O32: Exclude (BTB with Thales) | P32: Include | Q32: Grp B (OEM) | R32: 30 | T32: Thales | U32: A320-FAM030 | V32: 1
A33: 341 | B33: 10-458301-000 | C33: SAFRAN LANDING SYSTEMS (SAS) | D33: 32 | E33: HARNESS, 1M AXLE | F33: 2 | G33: 1 | H33: 500000 | I33: 2 | J33: 5230 | K33: Airbus web 23/3/26 | L33: 5230 | M33: Airbus web 23/3/26 | N33: 1 | O33: Include | P33: Include | Q33: Grp C (Others) | R33: 30 | U33: A320-FAM031 | V33: 1
A34: 337 | B34: 10-458501-000 | C34: SAFRAN LANDING SYSTEMS (SAS) | D34: 32 | E34: HARNESS, 2M AXLE | F34: 2 | G34: 1 | H34: 500000 | I34: 2 | J34: 6540 | K34: Airbus web 23/3/26 | L34: 6540 | M34: Airbus web 23/3/26 | N34: 1 | O34: Include | P34: Include | Q34: Grp C (Others) | R34: 30 | U34: A320-FAM032 | V34: 1
A35: 296 | B35: 10-385401-001 | C35: SAFRAN LANDING SYSTEMS (SAS) | D35: 32 | E35: HARNESS-2M ELECTRICAL | F35: 2 | G35: 3 | H35: 297900 | I35: 1 | J35: 18500 | K35: Airbus web 23/3/26 | L35: 18500 | M35: Airbus web 23/3/26 | N35: 1 | O35: Include | P35: Include | Q35: Grp C (Others) | R35: 30 | U35: A320-FAM033 | V35: 1
A36: 93 | B36: 10-386001-001 | C36: SAFRAN LANDING SYSTEMS (SAS) | D36: 32 | E36: RETRACTION ACTUATOR COMPLETE | F36: 2 | G36: 1 | H36: 37500 | I36: 1 | J36: 64160 | K36: Airbus web 23/3/26 | L36: 64160 | M36: Airbus web 23/3/26 | N36: 1 | O36: Include | P36: Include | Q36: Grp C (Others) | R36: 30 | U36: A320-FAM038 | V36: 1
A37: 247 | B37: 2A522-10000-000 | C37: DIEHL AEROSPACE GMBH | D37: 33 | E37: PSU-MINI EMERGENCY POWER SUPPLY UNIT,LIGHT | F37: 2 | G37: 3 | H37: 90000 | I37: 4 | J37: 3780 | K37: Airbus web 23/3/26 | L37: 3780 | M37: Airbus web 23/3/26 | N37: 1 | O37: Include | P37: Include | Q37: Grp C (Others) | R37: 30 | U37: A320-FAM039 | V37: 1
A38: 159 | B38: 2LA456884-01 | C38: GOODRICH LIGHTING SYSTEMS GMBH | D38: 33 | F38: 2 | G38: 3 | H38: 24881 | I38: 1 | J38: 21230 | K38: Airbus web 23/3/26 | L38: 21230 | M38: Airbus web 23/3/26 | N38: 1 | O38: Include | P38: Include | Q38: Grp C (Others) | R38: 30 | U38: A320-FAM040 | V38: 1
A39: 141 | B39: 2LA456884-02 | C39: GOODRICH LIGHTING SYSTEMS GMBH | D39: 33 | F39: 2 | G39: 3 | H39: 24881 | I39: 1 | J39: 21230 | K39: Airbus web 23/3/26 | L39: 21230 | M39: Airbus web 23/3/26 | N39: 1 | O39: Include | P39: Include | Q39: Grp C (Others) | R39: 30 | U39: A320-FAM041 | V39: 1
A40: 78 | B40: 822-3150-301 | C40: ROCKWELL COLLINS INC | D40: 34 | E40: TRANSCEIVER-WEATHER RADAR | F40: 2 | G40: 2 | H40: 36000 | I40: 1 | J40: 95370 | K40: Airbus web 23/3/26 | L40: 95370 | M40: Airbus web 23/3/26 | N40: 1 | O40: Include | P40: Include | Q40: Grp C (Others) | R40: 30 | T40: Rockwell Collins | U40: A320-FAM042 | V40: 1
A41: 208 | B41: CC3067-00 | C41: DIEHL AVIATION GILCHING GMBH | D41: 38 | E41: CABLE-CONTROL | F41: 2 | G41: 2 | H41: 25500 | I41: 1 | J41: 7190 | K41: Airbus web 23/3/26 | L41: 7190 | M41: Airbus web 23/3/26 | N41: 1 | O41: Include | P41: Include | Q41: Grp C (Others) | R41: 30 | U41: A320-FAM043 | V41: 1
A42: 180 | B42: AN3040-00 | C42: DIEHL AVIATION GILCHING GMBH | D42: 38 | E42: PANEL-INDICATION | F42: 2 | G42: 2 | H42: 45000 | I42: 1 | J42: 21870 | K42: Airbus web 23/3/26 | L42: 21870 | M42: Airbus web 23/3/26 | N42: 1 | O42: Include | P42: Include | Q42: Grp C (Others) | R42: 30 | U42: A320-FAM044 | V42: 1
A43: 85 | B43: 822-3613-100 | C43: ROCKWELL COLLINS INC | D43: 46 | E43: FOMAX UNIT | F43: 2 | G43: 2 | H43: 24000 | I43: 1 | J43: 57232 | K43: Rockwell Collins List Price 2026 | L43: 48166.667 | M43: 2025 RFQ AVG | N43: 0.84160376 | O43: Include | P43: Include | Q43: Grp C (Others) | R43: 30 | T43: Rockwell Collins | U43: A320-FAM045 | V43: 1
A44: 198 | B44: AL1000 | C44: SAM GMBH | D44: 52 | E44: ACTUATOR-FLIGHT LOCK L FWD OVERWING DOOR | F44: 2 | G44: 2 | H44: 76000 | I44: 4 | J44: 13568.58 | K44: Satair web 24/3/23 | L44: 13568.58 | M44: Satair web 24/3/23 | N44: 1 | O44: Include | P44: Include | Q44: Grp C (Others) | R44: 30 | U44: A320-FAM046 | V44: 1
A45: 233 | B45: 10-386101-001 | C45: SAFRAN LANDING SYSTEMS (SAS) | D45: 32 | E45: KIT-TPIS | F45: 2 | G45: 1 | H45: 179698 | I45: 1 | J45: 38080 | K45: Airbus web 23/3/26 | L45: 38080 | M45: Airbus web 23/3/26 | N45: 1 | O45: Exclude | P45: Exclude | S45: No | T45: Typically not supported under MBH | U45: #ERROR! | V45: 299
A46: 381 | B46: 10-387701-000 | C46: SAFRAN LANDING SYSTEMS | D46: 32 | E46: PLATE-KIT SERVICING | F46: 1 | G46: 1 | H46: 500000 | I46: 1 | J46: 438 | K46: Airbus web 23/3/26 | L46: 438 | M46: Airbus web 23/3/26 | N46: 1 | O46: Exclude | P46: Exclude | S46: No | T46: Low NUP | U46: #ERROR! | V46: 299
A47: 262 | B47: 14C15L21D700009 | C47: BE AEROSPACE SYSTEMS GMBH | D47: 35 | E47: CONTAINER ASSY-CHEMICAL OXYGEN,FOUR MASK | F47: 2 | G47: 2 | H47: 390000 | I47: 34 | J47: 1650 | K47: Airbus web 23/3/26 | L47: 1650 | M47: Airbus web 23/3/26 | N47: 1 | O47: Exclude | P47: Exclude | S47: No | T47: Typically not supported under MBH | U47: #ERROR! | V47: 299
A48: 260 | B48: 14C15R21D700009 | C48: BE AEROSPACE SYSTEMS GMBH | D48: 35 | E48: CONTAINER ASSY-CHEMICAL OXYGEN,FOUR MASK | F48: 2 | G48: 2 | H48: 390000 | I48: 35 | J48: 1650 | K48: Airbus web 23/3/26 | L48: 1650 | M48: Airbus web 23/3/26 | N48: 1 | O48: Exclude | P48: Exclude | S48: No | T48: Typically not supported under MBH | U48: #ERROR! | V48: 299
A49: 373 | B49: 20410-0101 | C49: SIMMONDS PRECISION PRODUCTS INC | D49: 28 | E49: FUEL-QUANTITY SENSOR | F49: 2 | G49: 2 | H49: 500000 | I49: 4 | J49: 575 | K49: Airbus web 23/3/26 | L49: 575 | M49: Airbus web 23/3/26 | N49: 1 | O49: Exclude | P49: Exclude | S49: No | T49: Likely Non-Repairable | U49: #ERROR! | V49: 299
A50: 251 | B50: 20412-0101 | C50: SIMMONDS PRECISION PRODUCTS INC | D50: 28 | E50: FUEL QUANTITY SENSOR | F50: 2 | G50: 3 | H50: 37500 | I50: 1 | J50: 5780 | K50: Airbus web 23/3/26 | L50: 5780 | M50: Airbus web 23/3/26 | N50: 1 | O50: Exclude | P50: Exclude | S50: No | T50: Likely Non-Repairable | U50: #ERROR! | V50: 299
A51: 288 | B51: 20412-0102 | C51: SIMMONDS PRECISION PRODUCTS INC | D51: 28 | E51: FUEL QUANTITY SENSOR | F51: 2 | G51: 3 | H51: 75000 | I51: 1 | J51: 5780 | K51: Airbus web 23/3/26 | L51: 5780 | M51: Airbus web 23/3/26 | N51: 1 | O51: Exclude | P51: Exclude | S51: No | T51: Likely Non-Repairable | U51: #ERROR! | V51: 299
A52: 195 | B52: 2428-82HE0310FF | C52: GOODRICH INTERIORS | D52: 25 | E52: SEAT-CABIN ATTENDANT | F52: 2 | G52: 2 | H52: 150000 | I52: 2 | J52: 23874 | K52: Collins Quote 25/3/26 | L52: 23874 | M52: Collins Quote 25/3/26 | N52: 1 | O52: Exclude | P52: Exclude | S52: No | T52: Typically not supported under MBH | U52: #ERROR! | V52: 299
A53: 237 | B53: 2428-82JE0310FF | C53: GOODRICH INTERIORS | D53: 25 | E53: SEAT-CABIN ATTENDANT | F53: 2 | G53: 2 | H53: 150000 | I53: 1 | J53: 23874 | K53: Collins Quote 25/3/26 | L53: 23874 | M53: Collins Quote 25/3/26 | N53: 1 | O53: Exclude | P53: Exclude | S53: No | T53: Typically not supported under MBH | U53: #ERROR! | V53: 299
A54: 238 | B54: 2428-82ME0310FF | C54: GOODRICH INTERIORS | D54: 25 | E54: SEAT-CABIN ATTENDANT | F54: 2 | G54: 2 | H54: 150000 | I54: 1 | J54: 23874 | K54: Collins Quote 25/3/26 | L54: 23874 | M54: Collins Quote 25/3/26 | N54: 1 | O54: Exclude | P54: Exclude | S54: No | T54: Typically not supported under MBH | U54: #ERROR! | V54: 299
A55: 179 | B55: 2430-12JK0030FF | C55: GOODRICH INTERIORS | D55: 25 | E55: SEAT-CABIN ATTENDANT | F55: 2 | G55: 2 | H55: 150000 | I55: 1 | J55: 66012 | K55: Collins Quote 25/3/26 | L55: 66012 | M55: Collins Quote 25/3/26 | N55: 1 | O55: Exclude | P55: Exclude | S55: No | T55: Typically not supported under MBH | U55: #ERROR! | V55: 299
A56: 358 | B56: 2LA005127-30 | C56: GOODRICH LIGHTING SYSTEMS GMBH | D56: 33 | F56: 6 | G56: 1 | H56: 145800 | I56: 1 | J56: 1750 | K56: Airbus web 23/3/26 | L56: 1750 | M56: Airbus web 23/3/26 | N56: 1 | O56: Exclude | P56: Exclude | S56: No | T56: Low NUP. High BER Reate | U56: #ERROR! | V56: 299
A57: 360 | B57: 2LA005128-30 | C57: GOODRICH LIGHTING SYSTEMS GMBH | D57: 33 | F57: 6 | G57: 1 | H57: 145800 | I57: 1 | J57: 1740 | K57: Airbus web 23/3/26 | L57: 1740 | M57: Airbus web 23/3/26 | N57: 1 | O57: Exclude | P57: Exclude | S57: No | T57: Low NUP. High BER Reate | U57: #ERROR! | V57: 299
A58: 362 | B58: 2LA005413-30 | C58: GOODRICH LIGHTING SYSTEMS GMBH | D58: 33 | F58: 6 | G58: 1 | H58: 145800 | I58: 1 | J58: 1760 | K58: Airbus web 23/3/26 | L58: 1760 | M58: Airbus web 23/3/26 | N58: 1 | O58: Exclude | P58: Exclude | S58: No | T58: Low NUP. High BER Reate | U58: #ERROR! | V58: 299
A59: 363 | B59: 2LA005414-30 | C59: GOODRICH LIGHTING SYSTEMS GMBH | D59: 33 | F59: 6 | G59: 1 | H59: 145800 | I59: 1 | J59: 1760 | K59: Airbus web 23/3/26 | L59: 1760 | M59: Airbus web 23/3/26 | N59: 1 | O59: Exclude | P59: Exclude | S59: No | T59: Low NUP. High BER Reate | U59: #ERROR! | V59: 299
A60: 342 | B60: 30-3761001-00 | C60: SAFRAN LANDING SYSTEMS (SAS) | D60: 32 | E60: COVER ASSY | F60: 6 | G60: 1 | H60: 100000 | I60: 1 | J60: 1660 | K60: Airbus web 23/3/26 | L60: 1660 | M60: Airbus web 23/3/26 | N60: 1 | O60: Exclude | P60: Exclude | S60: No | T60: Typically not supported under MBH | U60: #ERROR! | V60: 299
A61: 366 | B61: 3508802-71 | C61: EATON LIMITED | D61: 28 | E61: HOUSING-INDICATOR,MAGNETIC LEVEL | F61: 2 | G61: 2 | H61: 180000 | I61: 1 | J61: 2100 | K61: Airbus web 23/3/26 | L61: 2100 | M61: Airbus web 23/3/26 | N61: 1 | O61: Exclude | P61: Exclude | S61: No | T61: Likely high BER Rate | U61: #ERROR! | V61: 299
A62: 361 | B62: 3508803-641 | C62: EATON LIMITED | D62: 28 | E62: INDICATOR-MAGNETIC,LEVEL | F62: 6 | G62: 2 | H62: 120000 | I62: 1 | J62: 1460 | K62: Airbus web 23/3/26 | L62: 1460 | M62: Airbus web 23/3/26 | N62: 1 | O62: Exclude | P62: Exclude | S62: No | T62: Likely high BER Rate | U62: #ERROR! | V62: 299
A63: 395 | B63: 3559AAP | C63: AVOX SYSTEMS INC | D63: 35 | E63: CYLINDER ASSY-OXYGEN,PORTABLE | F63: 2 | G63: 2 | H63: 136500 | I63: 8 | J63: 3283.56 | K63: Safran Aerosystems 2026 | L63: 3283.56 | M63: Safran Aerosystems 2026 | N63: 1 | O63: Exclude | P63: Exclude | S63: No | T63: DG | U63: #ERROR! | V63: 299
A64: 389 | B64: 4323500-00-6600 | C64: B/E AEROSPACE INC | D64: 25 | E64: OVEN-STEAM | F64: 2 | G64: 3 | H64: 250000 | I64: 1 | J64: 23100 | K64: Airbus web 23/3/26 | L64: 23100 | M64: Airbus web 23/3/26 | N64: 1 | O64: Exclude | P64: Exclude | S64: No | T64: High Removal | U64: #ERROR! | V64: 299
A65: 390 | B65: 4323501-00-6600 | C65: B/E AEROSPACE INC | D65: 25 | E65: OVEN-STEAM | F65: 2 | G65: 3 | H65: 12000 | I65: 1 | J65: 20550 | K65: Airbus web 23/3/26 | L65: 20550 | M65: Airbus web 23/3/26 | N65: 1 | O65: Exclude | P65: Exclude | S65: No | T65: High Removal | U65: #ERROR! | V65: 299
A66: 388 | B66: 4661-2221-00 | C66: B/E AEROSPACE, INC. | D66: 25 | E66: HEATER-WATER | F66: 2 | G66: 3 | H66: 4800 | I66: 5 | J66: 10840 | K66: Airbus web 23/3/26 | L66: 10840 | M66: Airbus web 23/3/26 | N66: 1 | O66: Exclude | P66: Exclude | S66: No | T66: High Removal | U66: #ERROR! | V66: 299
A67: 230 | B67: 568-1-27202-008 | C67: EATON LIMITED | D67: 28 | E67: PUMP-FUEL | F67: 2 | G67: 1 | H67: 68400 | I67: 2 | J67: 7710 | K67: Airbus web 23/3/26 | L67: 7710 | M67: Airbus web 23/3/26 | N67: 1 | O67: Exclude | P67: Exclude | S67: No | T67: High BER Rate | U67: #ERROR! | V67: 299
A68: 368 | B68: 57-0005-1100 | C68: EATON LIMITED | D68: 28 | E68: MAGNETIC LEVEL INDICATOR-ROD | F68: 2 | G68: 1 | H68: 113377 | I68: 1 | J68: 1030 | K68: Airbus web 23/3/26 | L68: 1030 | M68: Airbus web 23/3/26 | N68: 1 | O68: Exclude | P68: Exclude | S68: No | T68: High BER Rate | U68: #ERROR! | V68: 299
A69: 256 | B69: 822-3594-100 | C69: ROCKWELL COLLINS INC | D69: 46 | E69: ANTENNA-FOMAX COCKPIT WIFI ANTENNA | F69: 2 | G69: 2 | H69: 36000 | I69: 1 | J69: 5020 | K69: Airbus web 23/3/26 | L69: 5020 | M69: Airbus web 23/3/26 | N69: 1 | O69: Exclude | P69: Exclude | S69: No | T69: Non Repairable | U69: #ERROR! | V69: 299
A70: 386 | B70: 8307-06-0000-01 | C70: SAFRAN CABIN GERMANY GMBH | D70: 25 | E70: EXTENDED OVEN | F70: 2 | G70: 3 | H70: 250000 | I70: 2 | J70: 225.4 | K70: Airbus web 23/3/26 (MOQ: 7) | L70: 225.4 | M70: Airbus web 23/3/26 (MOQ: 7) | N70: 1 | O70: Exclude | P70: Exclude | S70: No | T70: High Removal | U70: #ERROR! | V70: 299
A71: 387 | B71: 8307-56-0000-01 | C71: SAFRAN CABIN GERMANY GMBH | D71: 25 | E71: EXTENDED OVEN | F71: 2 | G71: 3 | H71: 250000 | I71: 2 | J71: 225.4 | K71: Airbus web 23/3/26 (MOQ: 7) | L71: 225.4 | M71: Airbus web 23/3/26 (MOQ: 7) | N71: 1 | O71: Exclude | P71: Exclude | S71: No | T71: High Removal | U71: #ERROR! | V71: 299
... A79: 151 | B79: WTA3050-00 | C79: DIEHL AVIATION GILCHING GMBH | D79: 38 | E79: WASTE TANK ASSY 220 | F79: 2 | G79: 3 | H79: 48750 | I79: 1 | J79: 40310 | K79: Airbus web 23/3/26 | L79: 40310 | M79: Airbus web 23/3/26 | N79: 1 | O79: Exclude | P79: Exclude | S79: No | T79: Typically not supported under MBH | U79: #ERROR! | V79: 299
A80: 134 | B80: E21328003 | C80: SAFRAN LANDING SYSTEMS | D80: 32 | E80: ABCU-ALTERNATE BRAKING CONTROL UNIT | F80: 2 | G80: 1 | H80: 22500 | I80: 1 | J80: 24480 | K80: Airbus web 23/3/26 | L80: 24480 | M80: Airbus web 23/3/26 | N80: 1 | O80: Include | P80: Include | Q80: Grp C (Others) | R80: 30 | U80: STEAS00002 | V80: 1
A81: 135 | B81: ACP4380AA120101 | C81: THALES AEROSPACE COMMUNICATIONS | D81: 23 | E81: ACP-AUDIO CONTROL PANEL | F81: 2 | G81: 2 | H81: 27600 | I81: 1 | J81: 29980 | K81: Airbus web 23/3/26 | L81: 29980 | M81: Airbus web 23/3/26 | N81: 1 | O81: Include | P81: Include | Q81: Grp C (Others) | R81: 30 | U81: STEAS00006 | V81: 2
A82: 133 | B82: ACP4380AA130101 | C82: THALES AEROSPACE COMMUNICATIONS | D82: 23 | E82: ACP-AUDIO CONTROL PANEL | F82: 2 | G82: 2 | H82: 27600 | I82: 1 | J82: 30640 | K82: Airbus web 23/3/26 | L82: 30640 | M82: Airbus web 23/3/26 | N82: 1 | O82: Include | P82: Include | Q82: Grp C (Others) | R82: 30 | U82: STEAS00006 | V82: 2
A83: 316 | B83: 334VZ01Y00 | C83: SAFRAN ELECTRONICS & DEFENSE | D83: 26 | E83: SWITCH | F83: 6 | G83: 1 | H83: 255000 | I83: 3 | J83: 3610 | K83: Airbus Web 12/03/26 | L83: 3610 | M83: Airbus Web 12/03/26 | N83: 1 | O83: Exclude | P83: Exclude | S83: No | T83: High BER Rate | U83: #ERROR! | V83: 299
A84: 98 | B84: 1071D0000-02 | C84: GOODRICH ACTUATION SYSTEMS LTD | D84: 27 | E84: ACTUATOR-FLAP | F84: 2 | G84: 1 | H84: 56250 | I84: 1 | J84: 86000 | K84: Airbus web 23/3/26 | L84: 86000 | M84: Airbus web 23/3/26 | N84: 1 | O84: Include | P84: Include | Q84: Grp C (Others) | R84: 30 | U84: STEAS00023 | V84: 1
A85: 47 | B85: 1072E0000-02 | C85: GOODRICH ACTUATION SYSTEMS LTD | D85: 27 | E85: ACTUATOR-FLAP | F85: 2 | G85: 1 | H85: 37500 | I85: 2 | J85: 86530 | K85: Airbus web 23/3/26 | L85: 86530 | M85: Airbus web 23/3/26 | N85: 1 | O85: Include | P85: Include | Q85: Grp C (Others) | R85: 30 | U85: STEAS00024 | V85: 1
A86: 51 | B86: 1075A0000-02 | C86: GOODRICH ACTUATION SYSTEMS LTD | D86: 27 | E86: ACTUATOR-FLAP | F86: 2 | G86: 1 | H86: 37500 | I86: 2 | J86: 80140 | K86: Airbus web 23/3/26 | L86: 80140 | M86: Airbus web 23/3/26 | N86: 1 | O86: Include | P86: Include | Q86: Grp C (Others) | R86: 30 | U86: STEAS00025 | V86: 1
A87: 70 | B87: 1074D0000-02 | C87: GOODRICH ACTUATION SYSTEMS LTD | D87: 27 | E87: ACTUATOR-FLAP | F87: 2 | G87: 1 | H87: 56250 | I87: 2 | J87: 84090 | K87: Airbus web 23/3/26 | L87: 84090 | M87: Airbus web 23/3/26 | N87: 1 | O87: Include | P87: Include | Q87: Grp C (Others) | R87: 30 | U87: STEAS00026 | V87: 1
A88: 192 | B88: E20000 | C88: SAM GMBH | D88: 52 | E88: ACTUATOR-HYDRAULIC | F88: 2 | G88: 2 | H88: 88350 | I88: 4 | J88: 9160 | K88: Airbus Web 16/03/26 | L88: 4333.3333 | M88: 2026 RFQ AVG | N88: 0.47307132 | O88: Include | P88: Include | Q88: Grp A (CRO) | R88: 30 | U88: #ERROR! | V88: 299
A89: 115 | B89: 4504086 | C89: APIC AUXILIARY POWER INT. CO. | D89: 49 | E89: ACTUATOR ASSY-IGV | F89: 2 | G89: 2 | H89: 18000 | I89: 1 | J89: 32450 | K89: Airbus Web 16/03/26 4510835 | L89: 32450 | M89: Airbus Web 16/03/26 4510835 | N89: 1 | O89: Include | P89: Include | Q89: Grp C (Others) | R89: 45 | U89: #ERROR! | V89: 299
A90: 90 | B90: 1809A0000-01 | C90: LIEBHERR AEROSPACE TOULOUSE SAS | D90: 21 | E90: ACTUATOR-INLET | F90: 2 | G90: 2 | H90: 30000 | I90: 2 | J90: 31590 | K90: Airbus Web 11/03/26 | L90: 17137.141 | M90: 2025 RFQ AVG | N90: 0.54248626 | O90: Include | P90: Include | Q90: Grp A (CRO) | R90: 30 | U90: #ERROR! | V90: 299
A91: 169 | B91: 10-452701-000 | C91: SAFRAN LANDING SYSTEMS (SAS) | D91: 32 | E91: ACTUATOR-LOCKSTAY | F91: 2 | G91: 1 | H91: 40000 | I91: 2 | J91: 12630 | K91: Airbus web 23/3/26 | L91: 12630 | M91: Airbus web 23/3/26 | N91: 1 | O91: Include | P91: Include | Q91: Grp A (CRO) | R91: 30 | U91: #ERROR! | V91: 299
A92: 187 | B92: 422082-400 | C92: GOODRICH ACTUATION SYSTEMS SAS | D92: 27 | E92: ACTUATOR-PITCH TRIM | F92: 2 | G92: 1 | H92: 150000 | I92: 1 | J92: 62610 | K92: Airbus Web 12/03/26 | L92: 62610 | M92: Airbus Web 12/03/26 | N92: 1 | O92: Include | P92: Include | Q92: Grp C (Others) | R92: 30 | U92: #ERROR! | V92: 299
A93: 54 | B93: 10-451702-000 | C93: SAFRAN LANDING SYSTEMS (SAS) | D93: 32 | E93: ACTUATOR-RETRACTION | F93: 2 | G93: 1 | H93: 25000 | I93: 2 | J93: 54190 | K93: Airbus web 23/3/26 | L93: 54190 | M93: Airbus web 23/3/26 | N93: 1 | O93: Include | P93: Include | Q93: Grp C (Others) | R93: 30 | U93: STEAS00036 | V93: 1
A94: 396 | B94: 6610-15946-2 | C94: NORD-MICRO GMBH & CO OHG | D94: 36 | E94: ACTUATOR-ROTARY | F94: 2 | G94: 2 | H94: 10588 | I94: 1 | J94: 7910 | K94: Airbus web 23/3/26 6610-20567-01 | L94: 7910 | M94: Airbus web 23/3/26 6610-20567-01 | N94: 1 | O94: Include | P94: Include | Q94: Grp C (Others) | R94: 30 | U94: #ERROR! | V94: 299
A95: 293 | B95: 6610-20560-01 | C95: NORD-MICRO GMBH & CO OHG | D95: 21 | E95: ACTUATOR-ROTARY | F95: 2 | G95: 2 | H95: 120000 | I95: 1 | J95: 8093.48 | K95: Satair - Nord Micro 2026 | L95: 8093.48 | M95: Satair - Nord Micro 2026 | N95: 1 | O95: Include | P95: Include | Q95: Grp A (CRO) | R95: 12 | U95: #ERROR! | V95: 299
... A100: 117 | B100: PG1152BC02 | C100: HONEYWELL INTERNATIONAL INC | D100: 34 | E100: ADM-AIR DATA MODULE | F100: 2 | G100: 2 | H100: 90000 | I100: 8 | J100: 23032.48 | K100: Honeywell web 25/3/26 | L100: 23032.48 | M100: Honeywell web 25/3/26 | N100: 1 | O100: Include | P100: Include | Q100: Grp C (Others) | R100: 30 | U100: #ERROR! | V100: 299
A101: 94 | B101: 87292325V07 | C101: THALES AVS FRANCE SAS | D101: 21 | E101: AEVC-AVIONICS EQUIPMENT VENTILATION COMPUTER | F101: 2 | G101: 2 | H101: 13500 | I101: 1 | J101: 20257 | K101: Thales Airline Price 2026 | L101: 5409.375 | M101: 2025 RFQ AVG | N101: 0.26703732 | O101: Exclude (BTB with Thales) | P101: Include | Q101: Grp B (OEM) | R101: 10 | T101: Thales | U101: #ERROR! | V101: 299
A102: 82 | B102: Z111H0040131 | C102: AIRBUS OPERATIONS GMBH | D102: 23 | E102: AIP-ATTENDANT INDICATION PANEL | F102: 2 | G102: 3 | H102: 15000 | I102: 4 | J102: 8029.07 | K102: Airbus Catalogue 2026 | L102: 8029.07 | M102: Airbus Catalogue 2026 | N102: 1 | O102: Include | P102: Include | Q102: Grp C (Others) | R102: 30 | U102: STEAS00052 | V102: 1
A103: 110 | B103: AMU4382AA110101 | C103: THALES AEROSPACE COMMUNICATIONS | D103: 23 | E103: AMU-AUDIO MANAGEMENT UNIT | F103: 2 | G103: 1 | H103: 43050 | I103: 1 | J103: 57680 | K103: Airbus web 23/3/26 | L103: 57680 | M103: Airbus web 23/3/26 | N103: 1 | O103: Include | P103: Include | Q103: Grp C (Others) | R103: 30 | U103: #ERROR! | V103: 299
A104: 310 | B104: 866-5034-010 | C104: ROCKWELL COLLINS INC | D104: 34 | E104: ANTENNA-RADIO ALTIMETER | F104: 2 | G104: 2 | H104: 135000 | I104: 4 | J104: 1760 | K104: Airbus web 23/3/26 | L104: 1760 | M104: Airbus web 23/3/26 | N104: 1 | O104: Exclude | P104: Exclude | S104: No | T104: Non Repairable | U104: #ERROR! | V104: 299
A105: 205 | B105: 071-50001-8104 | C105: HONEYWELL INTERNATIONAL INC | D105: 34 | E105: ANTENNA-TCAS | F105: 2 | G105: 2 | H105: 22500 | I105: 2 | J105: 37906.77 | K105: Honeywell web 25/3/26 | L105: 37906.77 | M105: Honeywell web 25/3/26 | N105: 1 | O105: Exclude | P105: Exclude | S105: No | T105: Non Repairable | U105: #ERROR! | V105: 299
A106: 249 | B106: 622-5137-601 | C106: ROCKWELL COLLINS INC | D106: 34 | E106: ANTENNA-WEATHER RADAR | F106: 6 | G106: 2 | H106: 135000 | I106: 1 | J106: 24312 | K106: Rockwell Collins List Price 2026 | L106: 4571 | M106: 2025 RFQ AVG | N106: 0.18801415 | O106: Exclude | P106: Exclude | S106: No | T106: Non Repairable | U106: #ERROR! | V106: 299
A107: 14 | B107: LA2T0G21006CA10 | C107: AIRBUS OPERATIONS SAS | D107: 46 | E107: ATSU-AIR TRAFFIC SERVICES UNIT | F107: 2 | G107: 3 | H107: 9000 | I107: 1 | J107: 168020 | K107: Airbus Avionics List Price 2026 | L107: 168020 | M107: Airbus Avionics List Price 2026 | N107: 1 | O107: Include | P107: Include | Q107: Grp C (Others) | R107: 10 | U107: #ERROR! | V107: 299
A108: 36 | B108: 35-0L5-1107-09 | C108: THALES AVS FRANCE SAS | D108: 24 | E108: BCL-BATTERY CHARGE LIMITER | F108: 2 | G108: 2 | H108: 7800 | I108: 2 | J108: 22143 | K108: Thales Airline Price 2026 | L108: 22143 | M108: Thales Airline Price 2026 | N108: 1 | O108: Exclude (BTB with Thales) | P108: Include | Q108: Grp B (OEM) | R108: 11 | T108: Thales | U108: #ERROR! | V108: 299
A109: 56 | B109: 787A0000-11 | C109: LIEBHERR-AEROSPACE LINDENBERG | D109: 27 | E109: BLOCK-VALVE | F109: 2 | G109: 1 | H109: 54000 | I109: 4 | J109: 53393.16 | K109: Liebherr 2026 | L109: 53393.16 | M109: Liebherr 2026 | N109: 1 | O109: Exclude (BTB with Liebherr) | P109: Include | Q109: Grp B (OEM) | R109: 30 | T109: Liebherr | U109: #ERROR! | V109: 299
A110: 123 | B110: 70418A020101 | C110: LIEBHERR AEROSPACE TOULOUSE SAS | D110: 36 | E110: BMC-BLEED MONITORING COMPUTER | F110: 2 | G110: 2 | H110: 48000 | I110: 2 | J110: 29580 | K110: Airbus web 23/3/26 | L110: 27000 | M110: 2025 RFQ AVG | N110: 0.9127789 | O110: Exclude (BTB with Liebherr) | P110: Include | Q110: Grp B (OEM) | R110: 30 | T110: Liebherr | U110: #ERROR! | V110: 299
A111: 222 | B111: AR4753-7 | C111: ADAMS RITE AEROSPACE, INC | D111: 25 | E111: BOLTING SYSTEM-DOOR,COCKPIT | F111: 2 | G111: 2 | H111: 27938 | I111: 1 | J111: 6860 | K111: Airbus web 23/3/26 | L111: 6860 | M111: Airbus web 23/3/26 | N111: 1 | O111: Exclude | P111: Exclude | S111: No | T111: High BER Rate | U111: #ERROR! | V111: 299
...

Sheet parameters
A1: Supported Fleet Statistics | F1: ESS CODE | G1: Tolerance Level
A2: Annual Flying Hours (per aircraft) | C2: see Column B in Provisioning Model tab | F2: 1 | G2: 0
A3: Total Repair Time (Including Freight) | C3: see Column J in Provisioning Model tab | F3: 2 | G3: 0
A4: CRF | B4: 0 | C4: 0-1 | F4: 3 | G4: 0
A8: Provisioning Criteria | B8: ESS | C8: Protection Level | D8: Minimum Annual Demand (MAD) | E8: Arisings TRT | F8: Actual TRT Demand | G8: Actual Fill Rate (TAT) | H8: Arisings TRT (Annual) | I8: Actual TRT Demand (Annual) | J8: Actual Fill Rate (Annual) | L8: Desired SL%
A9: Target Fill Rate % Ess 1 | B9: 1 | C9: 0.98 | D9: 0.1 | L9: 98
A10: Target Fill Rate % Ess 2 | B10: 2 | C10: 0.93 | D10: 0.1 | L10: 95
A11: Target Fill Rate % Ess 3 | B11: 3 | C11: 0.9 | D11: 0.1 | L11: 92
C12: Vary the Protection Level in Column C such that the "Actual Fill Rate" in Column G meets the Desired Service Level% in Column L
A16: PNs with #N/A output issues - record data if applicable
A17: Prt Number | B17: Selected MTBUR | C17: amended MTBUR

Sheet inhousePoolInfo
A1: To update below info MONTHLY based on latest FA report | I1: If PN is A320neo unique or B737MAX unique, do not consider famclass qty, only use Available Pool Qty by PN; Pool Qty by Famclass will include Pool Qty by FA PN, so do not double-count
E2: Mar 2026 data | K2: Mar 2026 data
A3: FA PN | B3: Famclass | C3: 1 Mar 2026 - FA Qty | D3: Available Pool Qty | E3: Highest NBV (SGD) | F3: Highest Monthly Depreciation (SGD) | I3: Available Pool Qty by Famclass | J3: Available Pool Qty | K3: Highest NBV (SGD) | L3: Highest Monthly Depreciation (SGD)
A4: 003CM00-0200 | B4: STEAS01324 | C4: 2 | D4: 1 | E4: 22542.61 | F4: 86.370133 | I4: STEAS00001 | J4: 8 | K4: 8087.62 | L4: 38.1492
A5: 003-CM-00-0200 | B5: STEAS01324 | C5: 1 | D5: 1 | E5: 24511.22 | F5: 87.85 | I5: STEAS00002 | J5: 4 | K5: 15980.86 | L5: 75.027533
A6: 003CM00-0400 | B6: STEAS01326 | C6: 1 | D6: 1 | E6: 15224.95 | F6: 72.8459 | I6: STEAS00003 | J6: 8 | K6: 15350.46 | L6: 60.197867
A7: 005RL03 | B7: STEAS00832 | C7: 2 | D7: 2 | E7: 323.08 | F7: 1.56 | I7: STEAS00004 | J7: 8 | K7: 5669.68 | L7: 30.157833
A8: 005RL05 | B8: STEAS00832 | C8: 1 | D8: 1 | E8: 15223.66 | F8: 67.07 | I8: STEAS00005 | J8: 4 | K8: 4376.66 | L8: 19.5386
A9: 0102ME2GE | B9: STEAS00415 | C9: 7 | D9: 7 | E9: 17995.16 | F9: 66.158667 | I9: STEAS00006 | J9: 20 | K9: 10650.99 | L9: 70.54
A10: 0123FA2 | B10: STEAS02237 | C10: 7 | D10: 4 | E10: 3956.76 | F10: 41.22 | I10: STEAS00008 | J10: 8 | K10: 11530.69 | L10: 62.328167
A11: 0154GL5 | B11: STEAS00418 | C11: 1 | D11: 1 | E11: 0 | F11: 0 | I11: STEAS00009 | J11: 1 | K11: 7737.16 | L11: 113.78
A12: 0154JU | B12: STEAS00975 | C12: 1 | D12: 1 | E12: 0 | F12: 0 | I12: STEAS00010 | J12: 10 | K12: 10181.36 | L12: 73.778056
A13: 0154MW-CLB | B13: STEAS06258 | C13: 2 | D13: 1 | E13: 40206.62 | F13: 134.92153 | I13: STEAS00012 | J13: 1 | K13: 3001.19 | L13: 14.024267
A14: 0154NE2 | B14: STEAS06257 | C14: 1 | D14: 1 | E14: 22468.63 | F14: 84.15 | I14: STEAS00015 | J14: 2 | K14: 0 | L14: 0
A15: 01N65900 | B15: STEAS00196 | C15: 7 | D15: 7 | E15: 1746.21 | F15: 20.0715 | I15: STEAS00016 | J15: 1 | K15: 37605.4 | L15: 139.797
... A32: 066-1093-11 | B32: STEAS02433 | C32: 1 | D32: 1 | E32: 0 | F32: 0 | I32: STEAS00034 | J32: 3 | K32: 7692.79 | L32: 36.458667
A33: 066-50000-1508 | C33: 1 | D33: 1 | E33: 0 | F33: 0 | I33: STEAS00035 | J33: 6 | K33: 22898.71 | L33: 107.00333
A34: 066-50000-2220 | B34: STEAS00113 | C34: 4 | D34: 4 | E34: 1802.1 | F34: 64.36 | I34: STEAS00036 | J34: 9 | K34: 40874.61 | L34: 158.42867
A35: 066-50000-2221 | B35: STEAS00113 | C35: 2 | D35: 1 | E35: 1588.42 | F35: 33.1 | I35: STEAS00037 | J35: 2 | K35: 1016.88 | L35: 19.55
A36: 066-50006-1202 | B36: STEAS00380 | C36: 1 | D36: 1 | E36: 0 | F36: 0 | I36: STEAS00038 | J36: 4 | K36: 5034.76 | L36: 16.838667
A37: 066-50007-0101 | B37: STEAS02438 | C37: 3 | D37: 0 | E37: 22932.52 | F37: 138.15 | I37: STEAS00040 | J37: 17 | K37: 36651.65 | L37: 349.06333
A38: 066-50007-0212 | B38: STEAS00481 | C38: 2 | D38: 2 | E38: 0 | F38: 0 | I38: STEAS00041 | J38: 6 | K38: 10076.58 | L38: 132.58
A39: 066-50007-0222 | B39: STEAS00481 | C39: 1 | D39: 1 | E39: 3044.1 | F39: 304.41 | I39: STEAS00043 | J39: 7 | K39: 274428 | L39: 1016.4
A40: 066-50007-0432 | B40: STEAS00481 | C40: 2 | D40: 2 | E40: 18767.95 | F40: 312.8 | I40: STEAS00044 | J40: 11 | K40: 2015.33 | L40: 28.79
A41: 066-50007-0531 | B41: STEAS02438 | C41: 1 | D41: 0 | E41: 11402.63 | F41: 44.89 | I41: STEAS00045 | J41: 3 | K41: 22622.93 | L41: 84.1001
A42: 066-50007-1531 | B42: STEAS01330 | C42: 4 | D42: 2 | E42: 106441.44 | F42: 403.18727 | I42: STEAS00046 | J42: 10 | K42: 4097.27 | L42: 15.1191
A43: 066-50008-0405 | B43: STEAS00483 | C43: 1 | D43: 1 | E43: 28561.13 | F43: 328.29 | I43: STEAS00047 | J43: 7 | K43: 3346.24 | L43: 39.37
A44: 066-50008-0406 | B44: STEAS00483 | C44: 3 | D44: 1 | E44: 0 | F44: 0 | I44: STEAS00048 | J44: 2 | K44: 0 | L44: 0
A45: 066-50008-0407 | B45: STEAS00483 | C45: 2 | D45: 2 | E45: 13487.18 | F45: 236.62 | I45: STEAS00049 | J45: 18 | K45: 445802.75 | L45: 1714.63
... A110: 1019439-1-001 | B110: STEAS02244 | C110: 3 | D110: 1 | E110: 55016.94 | F110: 221.84 | I110: STEAS00146 | J110: 12 | K110: 38573.61 | L110: 258.88333
A111: 1019439-2-001 | B111: STEAS02244 | C111: 1 | D111: 1 | E111: 76167.65 | F111: 337.025 | I111: STEAS00147 | J111: 0
A112: 1020420-2-114 | B112: STEAS00192 | C112: 1 | D112: 1 | E112: 1059331.2 | F112: 4996.8451 | I112: STEAS00148 | J112: 3 | K112: 76934.73 | L112: 289.22833
A113: 1020420-3-118 | B113: STEAS00192 | C113: 1 | D113: 1 | E113: 1184816.1 | F113: 4628.1879 | I113: STEAS00149 | J113: 6 | K113: 1282.96 | L113: 32.9
A114: 1020896-1 | B114: STEAS01265 | C114: 2 | D114: 2 | E114: 29471.04 | F114: 115.1212 | I114: STEAS00150 | J114: 2 | K114: 6410.33 | L114: 59.36
A115: 1020901-2 | B115: STEAS01266 | C115: 2 | D115: 1 | E115: 25082.87 | F115: 118.31543 | I115: STEAS00151 | J115: 4 | K115: 45862.62 | L115: 179.15087
A116: 1020902-1 | B116: STEAS01267 | C116: 1 | D116: 1 | E116: 5476.68 | F116: 25.712033 | I116: STEAS00154 | J116: 1 | K116: 17778.33 | L116: 67.088067
A117: 1020903-1 | B117: STEAS01268 | C117: 1 | D117: 1 | E117: 47700.02 | F117: 223.94 | I117: STEAS00155 | J117: 9 | K117: 20560.58 | L117: 147.92
A118: 1020923-1 | B118: STEAS01269 | C118: 2 | D118: 1 | E118: 99099.07 | F118: 387.10573 | I118: STEAS00156 | J118: 2 | K118: 704.78 | L118: 8.92
A119: 1020924-1 | B119: STEAS01270 | C119: 2 | D119: 1 | E119: 40012.28 | F119: 156.29803 | I119: STEAS00159 | J119: 1 | K119: 21270.34 | L119: 82.76
A120: 1020925-3 | B120: STEAS01271 | C120: 1 | D120: 1 | E120: 29430.3 | F120: 114.96207 | I120: STEAS00160 | J120: 10 | K120: 5584.72 | L120: 20.532
A121: 1020926-1 | B121: STEAS01272 | C121: 1 | D121: 0 | E121: 163503.28 | F121: 771.2418 | I121: STEAS00161 | J121: 26 | K121: 51996.82 | L121: 186.36853
A122: 1020926-2 | B122: STEAS01272 | C122: 2 | D122: 2 | E122: 202253.81 | F122: 754.6784 | I122: STEAS00162 | J122: 5 | K122: 48457.87 | L122: 187.1
A123: 1020927-1 | B123: STEAS01273 | C123: 2 | D123: 1 | E123: 61973.54 | F123: 242.08 | I123: STEAS00163 | J123: 2 | K123: 1346.22 | L123: 16.22
... A135: 1022310-1 | B135: STEAS01283 | C135: 2 | D135: 1 | E135: 122289.21 | F135: 477.69 | I135: STEAS00181 | J135: 3 | K135: 2376.9 | L135: 30.09
A136: 1023263-1 | C136: 2 | D136: 2 | E136: 28483.03 | F136: 133.7232 | I136: STEAS00182 | J136: 11 | K136: 21261.23 | L136: 236.24
A137: 1023264-4 | B137: STEAS00151 | C137: 1 | D137: 1 | E137: 39414.5 | F137: 185.0445 | I137: STEAS00183 | J137: 2 | K137: 172.4 | L137: 2.08
A138: 1023264-6 | B138: STEAS00151 | C138: 2 | D138: 2 | E138: 45862.62 | F138: 179.15087 | I138: STEAS00184 | J138: 15 | K138: 94989.79 | L138: 358.452
A139: 1023348-2-105 | B139: STEAS01286 | C139: 1 | D139: 1 | E139: 228724.42 | F139: 1073.8235 | I139: STEAS00186 | J139: 24 | K139: 166463.64 | L139: 642.71673
A140: 1023348-5-106 | B140: STEAS01286 | C140: 1 | D140: 1 | E140: 247645.65 | F140: 967.3658 | I140: STEAS00187 | J140: 1 | K140: 0 | L140: 0
A141: 1023448 | B141: STEAS04548 | C141: 1 | D141: 1 | E141: 57517.01 | F141: 270.0329 | I141: STEAS00188 | J141: 1 | K141: 428.68 | L141: 5.43
A142: 1023448-2 | B142: STEAS04548 | C142: 1 | D142: 1 | E142: 62848.41 | F142: 245.5016 | I142: STEAS00189 | J142: 2 | K142: 155886.71 | L142: 731.86
A143: 1023702-1 | B143: STEAS01287 | C143: 2 | D143: 1 | E143: 179142.38 | F143: 699.77493 | I143: STEAS00190 | J143: 8 | K143: 22262.01 | L143: 117.7884
A144: 1024-3 | B144: STEAS04080 | C144: 1 | D144: 1 | E144: 2340.78 | F144: 19.837167 | I144: STEAS00191 | J144: 7 | K144: 308003.2 | L144: 2124.16
A145: 1024-4 | B145: STEAS04080 | C145: 1 | D145: 1 | E145: 7890.65 | F145: 37.045233 | I145: STEAS00192 | J145: 2 | K145: 1184816.1 | L145: 4628.1879
A146: 1025044-2 | B146: STEAS00533 | C146: 2 | D146: 1 | E146: 42580.6 | F146: 166.3305 | I146: STEAS00194 | J146: 21 | K146: 31039.36 | L146: 115.388
A147: 1028828 | B147: STEAS01261 | C147: 1 | D147: 0 | E147: 28483.03 | F147: 133.7232 | I147: STEAS00195 | J147: 11 | K147: 53596.69 | L147: 409.13503
A148: 102AH2AG | B148: STEAS00415 | C148: 8 | D148: 3 | E148: 15293.21 | F148: 105.47044 | I148: STEAS00196 | J148: 36 | K148: 13888.77 | L148: 52.410467
... A151: 10-376001-000 | B151: STEAS00162 | C151: 1 | D151: 0 | E151: 48457.87 | F151: 187.1 | I151: STEAS00199 | J151: 20 | K151: 22381.24 | L151: 101.733
A152: 10-376001-000A | C152: 1 | D152: 1 | E152: 41341.09 | F152: 195.92933 | I152: STEAS00200 | J152: 19 | K152: 22381.24 | L152: 101.733
A153: 10-376701-000 | B153: STEAS01078 | C153: 1 | D153: 0 | E153: 2609.96 | F153: 12.369433 | I153: STEAS00201 | J153: 12 | K153: 52912.68 | L153: 269.96267
A154: 10-450701-000 | B154: STEAS00166 | C154: 3 | D154: 1 | E154: 28998.49 | F154: 109.01683 | I154: STEAS00202 | J154: 16 | K154: 2631.63 | L154: 18.797333
A155: 10-451401-000 | B155: STEAS00154 | C155: 1 | D155: 1 | E155: 17778.33 | F155: 67.088067 | I155: STEAS00203 | J155: 9 | K155: 5032.7 | L155: 26.488
A156: 10-451701-000 | B156: STEAS00036 | C156: 2 | D156: 1 | E156: 40874.61 | F156: 158.42867 | I156: STEAS00204 | J156: 13 | K156: 9299.36 | L156: 34.32
A157: 10-452701-000 | B157: STEAS00031 | C157: 1 | D157: 0 | E157: 7544.37 | F157: 38.102967 | I157: STEAS00206 | J157: 1 | K157: 2745.79 | L157: 10.2074
A158: 10500-1 | B158: STEAS04994 | C158: 1 | D158: 1 | E158: 0 | F158: 0 | I158: STEAS00207 | J158: 2 | K158: 2099.76 | L158: 15.326667
A159: 1058-34 | B159: STEAS01070 | C159: 3 | D159: 3 | E159: 7074.14 | F159: 26.200533 | I159: STEAS00208 | J159: 12 | K159: 66002.37 | L159: 709.70278
A160: 106-1-1100-02 | B160: STEAS00008 | C160: 8 | D160: 8 | E160: 11530.69 | F160: 62.328167 | I160: STEAS00209 | J160: 1 | K160: 0 | L160: 0
A161: 10-62035-2 | B161: STEAS02484 | C161: 1 | D161: 1 | E161: 2391.96 | F161: 32.76 | I161: STEAS00211 | J161: 15 | K161: 17431.82 | L161: 67.565167
A162: 10-62091-17 | B162: STEAS02272 | C162: 1 | D162: 0 | E162: 0 | F162: 0 | I162: STEAS00212 | J162: 5 | K162: 4959.66 | L162: 18.301333
A163: 10-631045-1 | B163: STEAS02507 | C163: 1 | D163: 1 | E163: 0 | F163: 0 | I163: STEAS00213 | J163: 3 | K163: 2173.82 | L163: 10.25
A164: 10-631045-2 | B164: STEAS00202 | C164: 12 | D164: 12 | E164: 937.22 | F164: 6.55 | I164: STEAS00214 | J164: 8 | K164: 5288.8 | L164: 25.065333
... A246: 11-6537-7 | B246: STEAS02370 | C246: 1 | D246: 1 | E246: 311.86 | F246: 2.64 | I246: STEAS00313 | J246: 3 | K246: 5312.62 | L246: 57.75
A247: 11-6537-9 | B247: STEAS02370 | C247: 4 | D247: 1 | E247: 1224.11 | F247: 5.49 | I247: STEAS00314 | J247: 0
A248: 116817-5 | B248: STEAS02571 | C248: 2 | D248: 2 | E248: 2115.53 | F248: 10.03 | I248: STEAS00315 | J248: 16 | K248: 22867.9 | L248: 86.29
A249: 116A1510-1 | B249: STEAS02572 | C249: 2 | D249: 2 | E249: 2822.48 | F249: 18.33 | I249: STEAS00316 | J249: 7 | K249: 1568.5 | L249: 46.13
A250: 116A1510-2 | B250: STEAS02573 | C250: 2 | D250: 1 | E250: 2822.48 | F250: 18.33 | I250: STEAS00317 | J250: 6 | K250: 17524.65 | L250: 135.85
A251: 116A1510-3 | B251: STEAS02572 | C251: 2 | D251: 1 | E251: 0 | F251: 0 | I251: STEAS00318 | J251: 3 | K251: 5513.87 | L251: 71.608889
A252: 116A1510-8 | B252: STEAS02573 | C252: 3 | D252: 3 | E252: 2846.19 | F252: 23.1399 | I252: STEAS00319 | J252: 2 | K252: 3782.11 | L252: 49.764722
A253: 1176-1 | B253: STEAS02579 | C253: 1 | D253: 1 | E253: 1064.78 | F253: 11.83 | I253: STEAS00320 | J253: 8 | K253: 29785.85 | L253: 110.7281
A254: 1180003-424-100 | B254: STEAS02363 | C254: 2 | D254: 0 | E254: 0 | F254: 0 | I254: STEAS00321 | J254: 32 | K254: 20294.98 | L254: 75.45
A255: 1180003-425-100 | B255: STEAS02364 | C255: 5 | D255: 3 | E255: 2030.13 | F255: 18.8 | I255: STEAS00322 | J255: 2 | K255: 8359.14 | L255: 31.074867
A256: 11-841193-4 | B256: STEAS00246 | C256: 6 | D256: 2 | E256: 5132.09 | F256: 30.188778 | I256: STEAS00323 | J256: 1 | K256: 0 | L256: 0
A257: 11-851154-6 | B257: STEAS00201 | C257: 3 | D257: 3 | E257: 151.52 | F257: 3.03 | I257: STEAS00324 | J257: 4 | K257: 6333.69 | L257: 29.596667
A258: 118736-12 | B258: STEAS03965 | C258: 1 | D258: 1 | E258: 1401.91 | F258: 12.08 | I258: STEAS00325 | J258: 3 | K258: 667.66 | L258: 6.2985667
A259: 1191-8 | B259: STEAS02581 | C259: 4 | D259: 4 | E259: 1488.41 | F259: 11.275833 | I259: STEAS00326 | J259: 1 | K259: 1451.06 | L259: 5.4144
... A326: 14330-004C2 | B326: STEAS00478 | C326: 4 | D326: 4 | E326: 6911.94 | F326: 75.955556 | I326: STEAS00416 | J326: 2 | K326: 1920.53 | L326: 10.32
A327: 14330-050 | B327: STEAS00522 | C327: 1 | D327: 1 | E327: 0 | F327: 0 | I327: STEAS00417 | J327: 0
A328: 14330-062 | B328: STEAS00522 | C328: 1 | D328: 1 | E328: 922.51 | F328: 4.39 | I328: STEAS00418 | J328: 3 | K328: 0 | L328: 0
A329: 14330-230 | B329: STEAS00522 | C329: 3 | D329: 3 | E329: 0 | F329: 0 | I329: STEAS00419 | J329: 3 | K329: 2059.15 | L329: 33.22
A330: 14330-350 | B330: STEAS00239 | C330: 2 | D330: 2 | E330: 46288.34 | F330: 310.66 | I330: STEAS00420 | J330: 0
A331: 14330-375 | B331: STEAS00239 | C331: 7 | D331: 7 | E331: 60460.8 | F331: 225.6 | I331: STEAS00423 | J331: 2 | K331: 0 | L331: 0
A332: 14401-085 | B332: STEAS00428 | C332: 1 | D332: 1 | E332: 3353.09 | F332: 15.967 | I332: STEAS00425 | J332: 2 | K332: 581.88 | L332: 7.66
A333: 14403-001 | B333: STEAS00472 | C333: 1 | D333: 1 | E333: 0 | F333: 0 | I333: STEAS00427 | J333: 3 | K333: 591.65 | L333: 8.22
A334: 14403-003C | B334: STEAS00504 | C334: 11 | D334: 9 | E334: 9006.87 | F334: 32.398833 | I334: STEAS00428 | J334: 1 | K334: 3353.09 | L334: 15.967
A335: 14403-085 | B335: STEAS00407 | C335: 4 | D335: 4 | E335: 721.09 | F335: 31.35 | I335: STEAS00429 | J335: 8 | K335: 16526.9 | L335: 220.36
A336: 14403-125 | B336: STEAS00407 | C336: 1 | D336: 1 | E336: 4530.13 | F336: 20.7803 | I336: STEAS00430 | J336: 4 | K336: 58745.91 | L336: 212.8475
A337: 14404-010 | B337: STEAS00806 | C337: 2 | D337: 2 | E337: 0 | F337: 0 | I337: STEAS00431 | J337: 8 | K337: 15596.28 | L337: 197.42
A338: 144-171-000-031 | B338: STEAS00847 | C338: 1 | D338: 1 | E338: 6966.19 | F338: 50.479722 | I338: STEAS00432 | J338: 11 | K338: 22767.11 | L338: 288.19
A339: 144-186-000-011 | B339: STEAS02629 | C339: 2 | D339: 2 | E339: 4276.93 | F339: 48.05 | I339: STEAS00433 | J339: 7 | K339: 2410.76 | L339: 32.578
A340: 144-187-000-011 | B340: STEAS02630 | C340: 1 | D340: 1 | E340: 12074.43 | F340: 56.16 | I340: STEAS00434 | J340: 9 | K340: 14126.16 | L340: 178.82
...

Sheet currentMbhFleet
A1: Backup Raw Data | C1: A320 | D1: A320 | E1: A320 | F1: A320 | G1: A320 | H1: A330 | I1: B787 | J1: B737 | K1: B737 | L1: B737 | M1: B737 | N1: B737 | O1: B737 | S1: vlookup & adjust data | U1: A320 | V1: A320 | W1: A320 | X1: A320 | Y1: A320 | Z1: A330 | AA1: B787 | AB1: B737 | AC1: B737 | AD1: B737 | AE1: B737 | AF1: B737 | AG1: B737 | AK1: Current MBH Fleet info (to check with Program team regularly)
S2: origin | T2: In-Service AC Count | U2: 12 | V2: 8 | W2: 17 | X2: 3 | Y2: 66 | Z2: 16 | AA2: 53 | AB2: 62 | AC2: 44 | AD2: 10 | AE2: 11 | AF2: 30 | AG2: 98
B3: In-Service AC Count | C3: 12 | D3: 8 | E3: 17 | F3: 3 | G3: 66 | H3: 16 | I3: 53 | J3: 62 | K3: 44 | L3: 10 | M3: 11 | N3: 30 | O3: 98 | S3: adjusted | T3: In-Service AC Count | U3: 12 | V3: 8 | W3: 19 | X3: 3 | Y3: 66 | Z3: 13 | AA3: 53 | AB3: 62 | AC3: 44 | AD3: 6 | AE3: 11 | AF3: 33 | AG3: 100 | AK3: Info as of 8 Dec 2025
A4: PN | B4: Commonality (to be updated) | C4: RAYA AIRWAYS A321CEO MBH | D4: TIGERAIR TAIWAN A320NEO | E4: China Airlines A321MBH | F4: JAL A321MBH | G4: Vietnam Air A321MBH VA2 | H4: China Airlines A330MBH | I4: JAL 787MBH | J4: JAL 737MBH | K4: Jeju 737Max MBH | L4: China Airlines | M4: Nok Air 737 (2025) | N4: T'way 737Max MBH | O4: Virgin Australia 737 MBH | P4: Program Count | Q4: Total AC Count | S4: PN | T4: Commonality (to be updated) | U4: RAYA AIRWAYS A321CEO MBH | V4: TIGERAIR TAIWAN A320NEO | W4: China Airlines A321MBH | X4: JAL A321MBH | Y4: Vietnam Air A321MBH VA2 | Z4: China Airlines A330MBH | AA4: JAL 787MBH | AB4: JAL 737MBH | AC4: Jeju 737Max MBH | AD4: China Airlines | AE4: Nok Air 737 (2025) | AF4: T'way 737Max MBH | AG4: Virgin Australia 737 MBH | AH4: Program Count | AI4: Total AC Count | AK4: A320 | AL4: In service | AM4: Contracted | AN4: In service | AO4: Contracted
A5: 00-5071-01 | E5: 1 | P5: 1 | S5: 00-5071-01 | U5: 0 | V5: 0 | W5: 19 | X5: 0 | Y5: 0 | Z5: 0 | AA5: 0 | AB5: 0 | AC5: 0 | AD5: 0 | AE5: 0 | AF5: 0 | AG5: 0 | AH5: 1 | AI5: 19 | AK5: Programme | AL5: CEO Fleet | AM5: CEO Fleet | AN5: NEO Fleet | AO5: NEO Fleet
A6: 005-RL-03 | G6: 1 | P6: 2 | S6: 005-RL-03 | U6: 0 | V6: 0 | W6: 0 | X6: 0 | Y6: 66 | Z6: 0 | AA6: 0 | AB6: 0 | AC6: 0 | AD6: 0 | AE6: 0 | AF6: 0 | AG6: 0 | AH6: 2 | AI6: 66 | AK6: China Airlines A321MBH | AL6: 0 | AM6: 0 | AN6: 19 | AO6: 19
A7: 005-RL-05 | C7: 1 | G7: 1 | P7: 3 | S7: 005-RL-05 | U7: 12 | V7: 0 | W7: 0 | X7: 0 | Y7: 66 | Z7: 0 | AA7: 0 | AB7: 0 | AC7: 0 | AD7: 0 | AE7: 0 | AF7: 0 | AG7: 0 | AH7: 3 | AI7: 78 | AK7: China Airlines A330MBH | AL7: 13 | AM7: 13 | AN7: 0 | AO7: 0
A8: 005-RL-05-0000 | G8: 1 | P8: 2 | S8: 005-RL-05-0000 | U8: 0 | V8: 0 | W8: 0 | X8: 0 | Y8: 66 | Z8: 0 | AA8: 0 | AB8: 0 | AC8: 0 | AD8: 0 | AE8: 0 | AF8: 0 | AG8: 0 | AH8: 2 | AI8: 66 | AK8: JAL A321MBH | AL8: 3 | AM8: 3
A9: 0102ME2GE | B9: A320-Common | D9: 1 | F9: 1 | P9: 5 | S9: 0102ME2GE | T9: A320-Common | U9: 0 | V9: 8 | W9: 0 | X9: 3 | Y9: 0 | Z9: 0 | AA9: 0 | AB9: 0 | AC9: 0 | AD9: 0 | AE9: 0 | AF9: 0 | AG9: 0 | AH9: 5 | AI9: 11 | AK9: RAYA AIRWAYS A321CEO MBH | AL9: 3 | AM9: 12 | AN9: 0 | AO9: 0
A10: 0123FA2 | B10: B737-Common | J10: 1 | K10: 1 | M10: 1 | N10: 1 | O10: 1 | P10: 5 | S10: 0123FA2 | T10: B737-Common | U10: 0 | V10: 0 | W10: 0 | X10: 0 | Y10: 0 | Z10: 0 | AA10: 0 | AB10: 62 | AC10: 44 | AD10: 0 | AE10: 11 | AF10: 33 | AG10: 100 | AH10: 5 | AI10: 250 | AK10: TIGERAIR TAIWAN A320NEO MBH | AL10: 0 | AM10: 0 | AN10: 8 | AO10: 8
A11: 0123FA2A | J11: 1 | K11: 1 | O11: 1 | P11: 3 | S11: 0123FA2A | U11: 0 | V11: 0 | W11: 0 | X11: 0 | Y11: 0 | Z11: 0 | AA11: 0 | AB11: 62 | AC11: 44 | AD11: 0 | AE11: 0 | AF11: 0 | AG11: 100 | AH11: 3 | AI11: 206 | AK11: Vietnam Air A321MBH | AL11: 43 | AM11: 43 | AN11: 23 | AO11: 23
A12: 0154JU | B12: A320-CEO | P12: 1 | S12: 0154JU | T12: A320-CEO | U12: 0 | V12: 0 | W12: 0 | X12: 0 | Y12: 0 | Z12: 0 | AA12: 0 | AB12: 0 | AC12: 0 | AD12: 0 | AE12: 0 | AF12: 0 | AG12: 0 | AH12: 1 | AI12: 0
A13: 01N65900 | B13: A320-Common | G13: 1 | K13: 1 | N13: 1 | P13: 4 | S13: 01N65900 | T13: A320-Common | U13: 0 | V13: 0 | W13: 0 | X13: 0 | Y13: 66 | Z13: 0 | AA13: 0 | AB13: 0 | AC13: 44 | AD13: 0 | AE13: 0 | AF13: 33 | AG13: 0 | AH13: 4 | AI13: 143
A14: 01N65910 | B14: B737-NG | M14: 1 | N14: 1 | P14: 2 | S14: 01N65910 | T14: B737-NG | U14: 0 | V14: 0 | W14: 0 | X14: 0 | Y14: 0 | Z14: 0 | AA14: 0 | AB14: 0 | AC14: 0 | AD14: 0 | AE14: 11 | AF14: 33 | AG14: 0 | AH14: 2 | AI14: 44 | AK14: B737 | AL14: In service | AM14: Contracted | AN14: In service | AO14: Contracted
A15: 01N65920 | B15: B787-Common | G15: 1 | N15: 1 | P15: 3 | S15: 01N65920 | T15: B787-Common | U15: 0 | V15: 0 | W15: 0 | X15: 0 | Y15: 66 | Z15: 0 | AA15: 0 | AB15: 0 | AC15: 0 | AD15: 0 | AE15: 0 | AF15: 33 | AG15: 0 | AH15: 3 | AI15: 99 | AK15: Programme | AL15: NG Fleet | AM15: NG Fleet | AN15: MAX Fleet | AO15: MAX Fleet
A16: 01N65920SKY | K16: 1 | P16: 1 | S16: 01N65920SKY | U16: 0 | V16: 0 | W16: 0 | X16: 0 | Y16: 0 | Z16: 0 | AA16: 0 | AB16: 0 | AC16: 44 | AD16: 0 | AE16: 0 | AF16: 0 | AG16: 0 | AH16: 1 | AI16: 44 | AK16: China Airlines 737 MBH | AL16: 6 | AM16: 6 | AN16: 0 | AO16: 0
A17: 0212KTU01 | P17: 2 | S17: 0212KTU01 | U17: 0 | V17: 0 | W17: 0 | X17: 0 | Y17: 0 | Z17: 0 | AA17: 0 | AB17: 0 | AC17: 0 | AD17: 0 | AE17: 0 | AF17: 0 | AG17: 0 | AH17: 2 | AI17: 0 | AK17: JAL 737MBH | AL17: 62 | AM17: 62
A18: 0212KTU03 | P18: 1 | S18: 0212KTU03 | U18: 0 | V18: 0 | W18: 0 | X18: 0 | Y18: 0 | Z18: 0 | AA18: 0 | AB18: 0 | AC18: 0 | AD18: 0 | AE18: 0 | AF18: 0 | AG18: 0 | AH18: 1 | AI18: 0 | AK18: Jeju 737Max MBH | AL18: 35 | AM18: 37 | AN18: 7 | AO18: 7
A19: 0212KTU04 | P19: 1 | S19: 0212KTU04 | U19: 0 | V19: 0 | W19: 0 | X19: 0 | Y19: 0 | Z19: 0 | AA19: 0 | AB19: 0 | AC19: 0 | AD19: 0 | AE19: 0 | AF19: 0 | AG19: 0 | AH19: 1 | AI19: 0 | AK19: Nok Air 737 (2025) MBH | AL19: 11 | AM19: 11 | AN19: 0 | AO19: 0
A20: 0212KTU05 | P20: 1 | S20: 0212KTU05 | U20: 0 | V20: 0 | W20: 0 | X20: 0 | Y20: 0 | Z20: 0 | AA20: 0 | AB20: 0 | AC20: 0 | AD20: 0 | AE20: 0 | AF20: 0 | AG20: 0 | AH20: 1 | AI20: 0 | AK20: T'way 737Max MBH | AL20: 28 | AM20: 28 | AN20: 5 | AO20: 5
A21: 0212KTU06 | P21: 1 | S21: 0212KTU06 | U21: 0 | V21: 0 | W21: 0 | X21: 0 | Y21: 0 | Z21: 0 | AA21: 0 | AB21: 0 | AC21: 0 | AD21: 0 | AE21: 0 | AF21: 0 | AG21: 0 | AH21: 1 | AI21: 0 | AK21: Virgin Australia 737 MBH | AL21: 86 | AM21: 86 | AN21: 14 | AO21: 14
A22: 0212KTU07 | P22: 1 | S22: 0212KTU07 | U22: 0 | V22: 0 | W22: 0 | X22: 0 | Y22: 0 | Z22: 0 | AA22: 0 | AB22: 0 | AC22: 0 | AD22: 0 | AE22: 0 | AF22: 0 | AG22: 0 | AH22: 1 | AI22: 0
A23: 0212KTU08 | P23: 1 | S23: 0212KTU08 | U23: 0 | V23: 0 | W23: 0 | X23: 0 | Y23: 0 | Z23: 0 | AA23: 0 | AB23: 0 | AC23: 0 | AD23: 0 | AE23: 0 | AF23: 0 | AG23: 0 | AH23: 1 | AI23: 0
A24: 0212KTU09 | P24: 2 | S24: 0212KTU09 | U24: 0 | V24: 0 | W24: 0 | X24: 0 | Y24: 0 | Z24: 0 | AA24: 0 | AB24: 0 | AC24: 0 | AD24: 0 | AE24: 0 | AF24: 0 | AG24: 0 | AH24: 2 | AI24: 0 | AK24: B787 | AL24: In service | AM24: Contracted | AN24: In service | AO24: Contracted
A25: 0212KTU10 | P25: 1 | S25: 0212KTU10 | U25: 0 | V25: 0 | W25: 0 | X25: 0 | Y25: 0 | Z25: 0 | AA25: 0 | AB25: 0 | AC25: 0 | AD25: 0 | AE25: 0 | AF25: 0 | AG25: 0 | AH25: 1 | AI25: 0 | AK25: Programme | AL25: B787-8 | AM25: B787-8 | AN25: B787-9 | AO25: B787-9
A26: 0212KTU11 | P26: 1 | S26: 0212KTU11 | U26: 0 | V26: 0 | W26: 0 | X26: 0 | Y26: 0 | Z26: 0 | AA26: 0 | AB26: 0 | AC26: 0 | AD26: 0 | AE26: 0 | AF26: 0 | AG26: 0 | AH26: 1 | AI26: 0 | AK26: JAL B787 | AL26: 22 | AM26: 22 | AN26: 31 | AO26: 31
A27: 0212KTU13 | P27: 2 | S27: 0212KTU13 | U27: 0 | V27: 0 | W27: 0 | X27: 0 | Y27: 0 | Z27: 0 | AA27: 0 | AB27: 0 | AC27: 0 | AD27: 0 | AE27: 0 | AF27: 0 | AG27: 0 | AH27: 2 | AI27: 0
A28: 0212KTU14 | P28: 1 | S28: 0212KTU14 | U28: 0 | V28: 0 | W28: 0 | X28: 0 | Y28: 0 | Z28: 0 | AA28: 0 | AB28: 0 | AC28: 0 | AD28: 0 | AE28: 0 | AF28: 0 | AG28: 0 | AH28: 1 | AI28: 0
A29: 0212KTU15 | P29: 1 | S29: 0212KTU15 | U29: 0 | V29: 0 | W29: 0 | X29: 0 | Y29: 0 | Z29: 0 | AA29: 0 | AB29: 0 | AC29: 0 | AD29: 0 | AE29: 0 | AF29: 0 | AG29: 0 | AH29: 1 | AI29: 0
A30: 0212KTU16 | P30: 2 | S30: 0212KTU16 | U30: 0 | V30: 0 | W30: 0 | X30: 0 | Y30: 0 | Z30: 0 | AA30: 0 | AB30: 0 | AC30: 0 | AD30: 0 | AE30: 0 | AF30: 0 | AG30: 0 | AH30: 2 | AI30: 0
A31: 0212KTU17 | P31: 1 | S31: 0212KTU17 | U31: 0 | V31: 0 | W31: 0 | X31: 0 | Y31: 0 | Z31: 0 | AA31: 0 | AB31: 0 | AC31: 0 | AD31: 0 | AE31: 0 | AF31: 0 | AG31: 0 | AH31: 1 | AI31: 0
A32: 024116 | B32: B737-Common | J32: 1 | P32: 1 | S32: 024116 | T32: B737-Common | U32: 0 | V32: 0 | W32: 0 | X32: 0 | Y32: 0 | Z32: 0 | AA32: 0 | AB32: 62 | AC32: 0 | AD32: 0 | AE32: 0 | AF32: 0 | AG32: 0 | AH32: 1 | AI32: 62
A33: 0270-0012-2 | B33: B787-Common | I33: 1 | P33: 1 | S33: 0270-0012-2 | T33: B787-Common | U33: 0 | V33: 0 | W33: 0 | X33: 0 | Y33: 0 | Z33: 0 | AA33: 53 | AB33: 0 | AC33: 0 | AD33: 0 | AE33: 0 | AF33: 0 | AG33: 0 | AH33: 1 | AI33: 53
A34: 0270-0014-3 | B34: B787-Common | I34: 1 | P34: 1 | S34: 0270-0014-3 | T34: B787-Common | U34: 0 | V34: 0 | W34: 0 | X34: 0 | Y34: 0 | Z34: 0 | AA34: 53 | AB34: 0 | AC34: 0 | AD34: 0 | AE34: 0 | AF34: 0 | AG34: 0 | AH34: 1 | AI34: 53
A35: 0270-0015-5 | I35: 1 | P35: 1 | S35: 0270-0015-5 | U35: 0 | V35: 0 | W35: 0 | X35: 0 | Y35: 0 | Z35: 0 | AA35: 53 | AB35: 0 | AC35: 0 | AD35: 0 | AE35: 0 | AF35: 0 | AG35: 0 | AH35: 1 | AI35: 53
A36: 0270-0016-4 | I36: 1 | P36: 1 | S36: 0270-0016-4 | U36: 0 | V36: 0 | W36: 0 | X36: 0 | Y36: 0 | Z36: 0 | AA36: 53 | AB36: 0 | AC36: 0 | AD36: 0 | AE36: 0 | AF36: 0 | AG36: 0 | AH36: 1 | AI36: 53
A37: 0600LS-04-00 | J37: 1 | P37: 1 | S37: 0600LS-04-00 | U37: 0 | V37: 0 | W37: 0 | X37: 0 | Y37: 0 | Z37: 0 | AA37: 0 | AB37: 62 | AC37: 0 | AD37: 0 | AE37: 0 | AF37: 0 | AG37: 0 | AH37: 1 | AI37: 62
A38: 06282 | G38: 1 | P38: 2 | S38: 06282 | U38: 0 | V38: 0 | W38: 0 | X38: 0 | Y38: 66 | Z38: 0 | AA38: 0 | AB38: 0 | AC38: 0 | AD38: 0 | AE38: 0 | AF38: 0 | AG38: 0 | AH38: 2 | AI38: 66
A39: 06283 | G39: 1 | P39: 2 | S39: 06283 | U39: 0 | V39: 0 | W39: 0 | X39: 0 | Y39: 66 | Z39: 0 | AA39: 0 | AB39: 0 | AC39: 0 | AD39: 0 | AE39: 0 | AF39: 0 | AG39: 0 | AH39: 2 | AI39: 66
A40: 064-50000-0110 | B40: B737-NG | K40: 1 | M40: 1 | N40: 1 | P40: 3 | S40: 064-50000-0110 | T40: B737-NG | U40: 0 | V40: 0 | W40: 0 | X40: 0 | Y40: 0 | Z40: 0 | AA40: 0 | AB40: 0 | AC40: 44 | AD40: 0 | AE40: 11 | AF40: 33 | AG40: 0 | AH40: 3 | AI40: 88
A41: 064-50000-2000 | B41: B737-NG | K41: 1 | M41: 1 | N41: 1 | P41: 3 | S41: 064-50000-2000 | T41: B737-NG | U41: 0 | V41: 0 | W41: 0 | X41: 0 | Y41: 0 | Z41: 0 | AA41: 0 | AB41: 0 | AC41: 44 | AD41: 0 | AE41: 11 | AF41: 33 | AG41: 0 | AH41: 3 | AI41: 88
A42: 065-50001-0200 | B42: A320-Common | D42: 1 | E42: 1 | G42: 1 | H42: 1 | P42: 6 | S42: 065-50001-0200 | T42: A320-Common | U42: 0 | V42: 8 | W42: 19 | X42: 0 | Y42: 66 | Z42: 13 | AA42: 0 | AB42: 0 | AC42: 0 | AD42: 0 | AE42: 0 | AF42: 0 | AG42: 0 | AH42: 6 | AI42: 106
A43: 066-01127-1301 | B43: B737-NG | K43: 1 | P43: 1 | S43: 066-01127-1301 | T43: B737-NG | U43: 0 | V43: 0 | W43: 0 | X43: 0 | Y43: 0 | Z43: 0 | AA43: 0 | AB43: 0 | AC43: 44 | AD43: 0 | AE43: 0 | AF43: 0 | AG43: 0 | AH43: 1 | AI43: 44
A44: 066-01127-1601 | K44: 1 | P44: 1 | S44: 066-01127-1601 | U44: 0 | V44: 0 | W44: 0 | X44: 0 | Y44: 0 | Z44: 0 | AA44: 0 | AB44: 0 | AC44: 44 | AD44: 0 | AE44: 0 | AF44: 0 | AG44: 0 | AH44: 1 | AI44: 44
A45: 066-01127-1602 | B45: B737-Common | K45: 1 | M45: 1 | N45: 1 | P45: 3 | S45: 066-01127-1602 | T45: B737-Common | U45: 0 | V45: 0 | W45: 0 | X45: 0 | Y45: 0 | Z45: 0 | AA45: 0 | AB45: 0 | AC45: 44 | AD45: 0 | AE45: 11 | AF45: 33 | AG45: 0 | AH45: 3 | AI45: 88
A46: 066-01212-0301 | B46: B737-Common | K46: 1 | N46: 1 | P46: 2 | S46: 066-01212-0301 | T46: B737-Common | U46: 0 | V46: 0 | W46: 0 | X46: 0 | Y46: 0 | Z46: 0 | AA46: 0 | AB46: 0 | AC46: 44 | AD46: 0 | AE46: 0 | AF46: 33 | AG46: 0 | AH46: 2 | AI46: 77
A47: 066-50000-2221 | B47: B737-Common | K47: 1 | P47: 1 | S47: 066-50000-2221 | T47: B737-Common | U47: 0 | V47: 0 | W47: 0 | X47: 0 | Y47: 0 | Z47: 0 | AA47: 0 | AB47: 0 | AC47: 44 | AD47: 0 | AE47: 0 | AF47: 0 | AG47: 0 | AH47: 1 | AI47: 44
A48: 066-50007-0101 | B48: B737-Common | K48: 1 | M48: 1 | N48: 1 | P48: 3 | S48: 066-50007-0101 | T48: B737-Common | U48: 0 | V48: 0 | W48: 0 | X48: 0 | Y48: 0 | Z48: 0 | AA48: 0 | AB48: 0 | AC48: 44 | AD48: 0 | AE48: 11 | AF48: 33 | AG48: 0 | AH48: 3 | AI48: 88
A49: 066-50007-0111 | K49: 1 | N49: 1 | P49: 2 | S49: 066-50007-0111 | U49: 0 | V49: 0 | W49: 0 | X49: 0 | Y49: 0 | Z49: 0 | AA49: 0 | AB49: 0 | AC49: 44 | AD49: 0 | AE49: 0 | AF49: 33 | AG49: 0 | AH49: 2 | AI49: 77
A50: 066-50007-0531 | B50: B737-NG | K50: 1 | M50: 1 | N50: 1 | P50: 3 | S50: 066-50007-0531 | T50: B737-NG | U50: 0 | V50: 0 | W50: 0 | X50: 0 | Y50: 0 | Z50: 0 | AA50: 0 | AB50: 0 | AC50: 44 | AD50: 0 | AE50: 11 | AF50: 33 | AG50: 0 | AH50: 3 | AI50: 88
A51: 066-50008-0405 | B51: A320-CEO | C51: 1 | P51: 1 | S51: 066-50008-0405 | T51: A320-CEO | U51: 12 | V51: 0 | W51: 0 | X51: 0 | Y51: 0 | Z51: 0 | AA51: 0 | AB51: 0 | AC51: 0 | AD51: 0 | AE51: 0 | AF51: 0 | AG51: 0 | AH51: 1 | AI51: 12
A52: 066-50008-0406 | B52: B737-NG | K52: 1 | M52: 1 | N52: 1 | P52: 3 | S52: 066-50008-0406 | T52: B737-NG | U52: 0 | V52: 0 | W52: 0 | X52: 0 | Y52: 0 | Z52: 0 | AA52: 0 | AB52: 0 | AC52: 44 | AD52: 0 | AE52: 11 | AF52: 33 | AG52: 0 | AH52: 3 | AI52: 88
A53: 066-50008-0408 | B53: B737-Common | K53: 1 | M53: 1 | N53: 1 | P53: 3 | S53: 066-50008-0408 | T53: B737-Common | U53: 0 | V53: 0 | W53: 0 | X53: 0 | Y53: 0 | Z53: 0 | AA53: 0 | AB53: 0 | AC53: 44 | AD53: 0 | AE53: 11 | AF53: 33 | AG53: 0 | AH53: 3 | AI53: 88
A54: 066-50012-0101 | B54: B737-NG | M54: 1 | N54: 1 | P54: 2 | S54: 066-50012-0101 | T54: B737-NG | U54: 0 | V54: 0 | W54: 0 | X54: 0 | Y54: 0 | Z54: 0 | AA54: 0 | AB54: 0 | AC54: 0 | AD54: 0 | AE54: 11 | AF54: 33 | AG54: 0 | AH54: 2 | AI54: 44
A55: 066-50012-0202 | B55: A320-CEO | C55: 1 | P55: 1 | S55: 066-50012-0202 | T55: A320-CEO | U55: 12 | V55: 0 | W55: 0 | X55: 0 | Y55: 0 | Z55: 0 | AA55: 0 | AB55: 0 | AC55: 0 | AD55: 0 | AE55: 0 | AF55: 0 | AG55: 0 | AH55: 1 | AI55: 12
A56: 066-50012-1212 | F56: 1 | P56: 1 | S56: 066-50012-1212 | U56: 0 | V56: 0 | W56: 0 | X56: 3 | Y56: 0 | Z56: 0 | AA56: 0 | AB56: 0 | AC56: 0 | AD56: 0 | AE56: 0 | AF56: 0 | AG56: 0 | AH56: 1 | AI56: 3
A57: 066-50013-0101 | B57: B737-Common | K57: 1 | N57: 1 | P57: 2 | S57: 066-50013-0101 | T57: B737-Common | U57: 0 | V57: 0 | W57: 0 | X57: 0 | Y57: 0 | Z57: 0 | AA57: 0 | AB57: 0 | AC57: 44 | AD57: 0 | AE57: 0 | AF57: 33 | AG57: 0 | AH57: 2 | AI57: 77
A58: 066-50013-0111 | B58: B737-NG | K58: 1 | L58: 1 | M58: 1 | P58: 3 | S58: 066-50013-0111 | T58: B737-NG | U58: 0 | V58: 0 | W58: 0 | X58: 0 | Y58: 0 | Z58: 0 | AA58: 0 | AB58: 0 | AC58: 44 | AD58: 6 | AE58: 11 | AF58: 0 | AG58: 0 | AH58: 3 | AI58: 61
A59: 066-50013-0202 | B59: A320-Common | C59: 1 | P59: 1 | S59: 066-50013-0202 | T59: A320-Common | U59: 12 | V59: 0 | W59: 0 | X59: 0 | Y59: 0 | Z59: 0 | AA59: 0 | AB59: 0 | AC59: 0 | AD59: 0 | AE59: 0 | AF59: 0 | AG59: 0 | AH59: 1 | AI59: 12
A60: 066-50014-0101 | B60: B737-NG | M60: 1 | N60: 1 | P60: 2 | S60: 066-50014-0101 | T60: B737-NG | U60: 0 | V60: 0 | W60: 0 | X60: 0 | Y60: 0 | Z60: 0 | AA60: 0 | AB60: 0 | AC60: 0 | AD60: 0 | AE60: 11 | AF60: 33 | AG60: 0 | AH60: 2 | AI60: 44
A61: 066-50014-0202 | B61: A320-Common | C61: 1 | F61: 1 | P61: 2 | S61: 066-50014-0202 | T61: A320-Common | U61: 12 | V61: 0 | W61: 0 | X61: 3 | Y61: 0 | Z61: 0 | AA61: 0 | AB61: 0 | AC61: 0 | AD61: 0 | AE61: 0 | AF61: 0 | AG61: 0 | AH61: 2 | AI61: 15
A62: 066-50014-1101 | B62: B787-Common | I62: 1 | P62: 1 | S62: 066-50014-1101 | T62: B787-Common | U62: 0 | V62: 0 | W62: 0 | X62: 0 | Y62: 0 | Z62: 0 | AA62: 53 | AB62: 0 | AC62: 0 | AD62: 0 | AE62: 0 | AF62: 0 | AG62: 0 | AH62: 1 | AI62: 53
A63: 066-50014-1501 | M63: 1 | P63: 1 | S63: 066-50014-1501 | U63: 0 | V63: 0 | W63: 0 | X63: 0 | Y63: 0 | Z63: 0 | AA63: 0 | AB63: 0 | AC63: 0 | AD63: 0 | AE63: 11 | AF63: 0 | AG63: 0 | AH63: 1 | AI63: 11
A64: 066-50029-1101 | B64: B737-NG | K64: 1 | M64: 1 | N64: 1 | P64: 3 | S64: 066-50029-1101 | T64: B737-NG | U64: 0 | V64: 0 | W64: 0 | X64: 0 | Y64: 0 | Z64: 0 | AA64: 0 | AB64: 0 | AC64: 44 | AD64: 0 | AE64: 11 | AF64: 33 | AG64: 0 | AH64: 3 | AI64: 88
A65: 066-50029-1201 | B65: B737-NG | K65: 1 | M65: 1 | N65: 1 | P65: 3 | S65: 066-50029-1201 | T65: B737-NG | U65: 0 | V65: 0 | W65: 0 | X65: 0 | Y65: 0 | Z65: 0 | AA65: 0 | AB65: 0 | AC65: 44 | AD65: 0 | AE65: 11 | AF65: 33 | AG65: 0 | AH65: 3 | AI65: 88
A66: 071-01503-2601 | B66: B737-Common | K66: 1 | M66: 1 | N66: 1 | P66: 3 | S66: 071-01503-2601 | T66: B737-Common | U66: 0 | V66: 0 | W66: 0 | X66: 0 | Y66: 0 | Z66: 0 | AA66: 0 | AB66: 0 | AC66: 44 | AD66: 0 | AE66: 11 | AF66: 33 | AG66: 0 | AH66: 3 | AI66: 88
A67: 0711480-004 | B67: A320-CEO | G67: 1 | P67: 3 | S67: 0711480-004 | T67: A320-CEO | U67: 0 | V67: 0 | W67: 0 | X67: 0 | Y67: 66 | Z67: 0 | AA67: 0 | AB67: 0 | AC67: 0 | AD67: 0 | AE67: 0 | AF67: 0 | AG67: 0 | AH67: 3 | AI67: 66
A68: 0711480-007 | G68: 1 | P68: 2 | S68: 0711480-007 | U68: 0 | V68: 0 | W68: 0 | X68: 0 | Y68: 66 | Z68: 0 | AA68: 0 | AB68: 0 | AC68: 0 | AD68: 0 | AE68: 0 | AF68: 0 | AG68: 0 | AH68: 2 | AI68: 66
A69: 071-50001-8102 | B69: B737-Common | K69: 1 | L69: 1 | M69: 1 | N69: 1 | P69: 4 | S69: 071-50001-8102 | T69: B737-Common | U69: 0 | V69: 0 | W69: 0 | X69: 0 | Y69: 0 | Z69: 0 | AA69: 0 | AB69: 0 | AC69: 44 | AD69: 6 | AE69: 11 | AF69: 33 | AG69: 0 | AH69: 4 | AI69: 94
A70: 071-50001-8104 | B70: A320-Common | P70: 1 | S70: 071-50001-8104 | T70: A320-Common | U70: 0 | V70: 0 | W70: 0 | X70: 0 | Y70: 0 | Z70: 0 | AA70: 0 | AB70: 0 | AC70: 0 | AD70: 0 | AE70: 0 | AF70: 0 | AG70: 0 | AH70: 1 | AI70: 0
A71: 0725185 | D71: 1 | F71: 1 | P71: 3 | S71: 0725185 | U71: 0 | V71: 8 | W71: 0 | X71: 3 | Y71: 0 | Z71: 0 | AA71: 0 | AB71: 0 | AC71: 0 | AD71: 0 | AE71: 0 | AF71: 0 | AG71: 0 | AH71: 3 | AI71: 11
A72: 0727540 | B72: A320-Common | C72: 1 | F72: 1 | G72: 1 | P72: 5 | S72: 0727540 | T72: A320-Common | U72: 12 | V72: 0 | W72: 0 | X72: 3 | Y72: 66 | Z72: 0 | AA72: 0 | AB72: 0 | AC72: 0 | AD72: 0 | AE72: 0 | AF72: 0 | AG72: 0 | AH72: 5 | AI72: 81
A73: 07323P000-01 | B73: B737-Common | J73: 1 | O73: 1 | P73: 2 | S73: 07323P000-01 | T73: B737-Common | U73: 0 | V73: 0 | W73: 0 | X73: 0 | Y73: 0 | Z73: 0 | AA73: 0 | AB73: 62 | AC73: 0 | AD73: 0 | AE73: 0 | AF73: 0 | AG73: 100 | AH73: 2 | AI73: 162
A74: 07324P000-01 | B74: B737-Common | J74: 1 | O74: 1 | P74: 2 | S74: 07324P000-01 | T74: B737-Common | U74: 0 | V74: 0 | W74: 0 | X74: 0 | Y74: 0 | Z74: 0 | AA74: 0 | AB74: 62 | AC74: 0 | AD74: 0 | AE74: 0 | AF74: 0 | AG74: 100 | AH74: 2 | AI74: 162
A75: 07325P000-01 | B75: B737-Common | J75: 1 | K75: 1 | O75: 1 | P75: 3 | S75: 07325P000-01 | T75: B737-Common | U75: 0 | V75: 0 | W75: 0 | X75: 0 | Y75: 0 | Z75: 0 | AA75: 0 | AB75: 62 | AC75: 44 | AD75: 0 | AE75: 0 | AF75: 0 | AG75: 100 | AH75: 3 | AI75: 206
A76: 0800LS-08 | J76: 1 | P76: 1 | S76: 0800LS-08 | U76: 0 | V76: 0 | W76: 0 | X76: 0 | Y76: 0 | Z76: 0 | AA76: 0 | AB76: 62 | AC76: 0 | AD76: 0 | AE76: 0 | AF76: 0 | AG76: 0 | AH76: 1 | AI76: 62
A77: 0800LS-08-00-00 | J77: 1 | P77: 1 | S77: 0800LS-08-00-00 | U77: 0 | V77: 0 | W77: 0 | X77: 0 | Y77: 0 | Z77: 0 | AA77: 0 | AB77: 62 | AC77: 0 | AD77: 0 | AE77: 0 | AF77: 0 | AG77: 0 | AH77: 1 | AI77: 62
A78: 0800LS-08-00-02 | J78: 1 | P78: 1 | S78: 0800LS-08-00-02 | U78: 0 | V78: 0 | W78: 0 | X78: 0 | Y78: 0 | Z78: 0 | AA78: 0 | AB78: 62 | AC78: 0 | AD78: 0 | AE78: 0 | AF78: 0 | AG78: 0 | AH78: 1 | AI78: 62
A79: 0800LS-08-00-03 | J79: 1 | P79: 1 | S79: 0800LS-08-00-03 | U79: 0 | V79: 0 | W79: 0 | X79: 0 | Y79: 0 | Z79: 0 | AA79: 0 | AB79: 62 | AC79: 0 | AD79: 0 | AE79: 0 | AF79: 0 | AG79: 0 | AH79: 1 | AI79: 62
A80: 0800LS-08-00-05 | J80: 1 | P80: 1 | S80: 0800LS-08-00-05 | U80: 0 | V80: 0 | W80: 0 | X80: 0 | Y80: 0 | Z80: 0 | AA80: 0 | AB80: 62 | AC80: 0 | AD80: 0 | AE80: 0 | AF80: 0 | AG80: 0 | AH80: 1 | AI80: 62
A81: 080-20705-01 | B81: B737-Common | J81: 1 | L81: 1 | M81: 1 | N81: 1 | O81: 1 | P81: 5 | S81: 080-20705-01 | T81: B737-Common | U81: 0 | V81: 0 | W81: 0 | X81: 0 | Y81: 0 | Z81: 0 | AA81: 0 | AB81: 62 | AC81: 0 | AD81: 6 | AE81: 11 | AF81: 33 | AG81: 100 | AH81: 5 | AI81: 212
A82: 0804LS-01 | J82: 1 | P82: 1 | S82: 0804LS-01 | U82: 0 | V82: 0 | W82: 0 | X82: 0 | Y82: 0 | Z82: 0 | AA82: 0 | AB82: 62 | AC82: 0 | AD82: 0 | AE82: 0 | AF82: 0 | AG82: 0 | AH82: 1 | AI82: 62
A83: 0851HL | F83: 1 | P83: 2 | S83: 0851HL | U83: 0 | V83: 0 | W83: 0 | X83: 3 | Y83: 0 | Z83: 0 | AA83: 0 | AB83: 0 | AC83: 0 | AD83: 0 | AE83: 0 | AF83: 0 | AG83: 0 | AH83: 2 | AI83: 3
A84: 0851HT-1 | K84: 1 | P84: 1 | S84: 0851HT-1 | U84: 0 | V84: 0 | W84: 0 | X84: 0 | Y84: 0 | Z84: 0 | AA84: 0 | AB84: 0 | AC84: 44 | AD84: 0 | AE84: 0 | AF84: 0 | AG84: 0 | AH84: 1 | AI84: 44
A85: 0851MC | D85: 1 | E85: 1 | F85: 1 | H85: 1 | P85: 5 | S85: 0851MC | U85: 0 | V85: 8 | W85: 19 | X85: 3 | Y85: 0 | Z85: 13 | AA85: 0 | AB85: 0 | AC85: 0 | AD85: 0 | AE85: 0 | AF85: 0 | AG85: 0 | AH85: 5 | AI85: 43
A86: 0861ED | B86: A320-CEO | G86: 1 | P86: 3 | S86: 0861ED | T86: A320-CEO | U86: 0 | V86: 0 | W86: 0 | X86: 0 | Y86: 66 | Z86: 0 | AA86: 0 | AB86: 0 | AC86: 0 | AD86: 0 | AE86: 0 | AF86: 0 | AG86: 0 | AH86: 3 | AI86: 66
A87: 0861ED2 | G87: 1 | P87: 3 | S87: 0861ED2 | U87: 0 | V87: 0 | W87: 0 | X87: 0 | Y87: 66 | Z87: 0 | AA87: 0 | AB87: 0 | AC87: 0 | AD87: 0 | AE87: 0 | AF87: 0 | AG87: 0 | AH87: 3 | AI87: 66
A88: 0861FL1 | B88: B737-Common | L88: 1 | M88: 1 | N88: 1 | O88: 1 | P88: 4 | S88: 0861FL1 | T88: B737-Common | U88: 0 | V88: 0 | W88: 0 | X88: 0 | Y88: 0 | Z88: 0 | AA88: 0 | AB88: 0 | AC88: 0 | AD88: 6 | AE88: 11 | AF88: 33 | AG88: 100 | AH88: 4 | AI88: 150
A89: 0871DP3 | P89: 1 | S89: 0871DP3 | U89: 0 | V89: 0 | W89: 0 | X89: 0 | Y89: 0 | Z89: 0 | AA89: 0 | AB89: 0 | AC89: 0 | AD89: 0 | AE89: 0 | AF89: 0 | AG89: 0 | AH89: 1 | AI89: 0
A90: 0871DP4 | B90: A330-CEO | P90: 1 | S90: 0871DP4 | T90: A330-CEO | U90: 0 | V90: 0 | W90: 0 | X90: 0 | Y90: 0 | Z90: 0 | AA90: 0 | AB90: 0 | AC90: 0 | AD90: 0 | AE90: 0 | AF90: 0 | AG90: 0 | AH90: 1 | AI90: 0
A91: 0871DP5-1 | B91: A320-CEO | E91: 1 | H91: 1 | P91: 3 | S91: 0871DP5-1 | T91: A320-CEO | U91: 0 | V91: 0 | W91: 19 | X91: 0 | Y91: 0 | Z91: 13 | AA91: 0 | AB91: 0 | AC91: 0 | AD91: 0 | AE91: 0 | AF91: 0 | AG91: 0 | AH91: 3 | AI91: 32
A92: 088256-04644 | B92: A320-Common | C92: 1 | D92: 1 | F92: 1 | G92: 1 | P92: 7 | S92: 088256-04644 | T92: A320-Common | U92: 12 | V92: 8 | W92: 0 | X92: 3 | Y92: 66 | Z92: 0 | AA92: 0 | AB92: 0 | AC92: 0 | AD92: 0 | AE92: 0 | AF92: 0 | AG92: 0 | AH92: 7 | AI92: 89
A93: 0A090-0649 | K93: 1 | N93: 1 | P93: 2 | S93: 0A090-0649 | U93: 0 | V93: 0 | W93: 0 | X93: 0 | Y93: 0 | Z93: 0 | AA93: 0 | AB93: 0 | AC93: 44 | AD93: 0 | AE93: 0 | AF93: 33 | AG93: 0 | AH93: 2 | AI93: 77
A94: 0A220-0267 | K94: 1 | P94: 1 | S94: 0A220-0267 | U94: 0 | V94: 0 | W94: 0 | X94: 0 | Y94: 0 | Z94: 0 | AA94: 0 | AB94: 0 | AC94: 44 | AD94: 0 | AE94: 0 | AF94: 0 | AG94: 0 | AH94: 1 | AI94: 44
A95: 0A220-0271 | K95: 1 | P95: 1 | S95: 0A220-0271 | U95: 0 | V95: 0 | W95: 0 | X95: 0 | Y95: 0 | Z95: 0 | AA95: 0 | AB95: 0 | AC95: 44 | AD95: 0 | AE95: 0 | AF95: 0 | AG95: 0 | AH95: 1 | AI95: 44
A96: 0A226-0359CK | K96: 1 | P96: 1 | S96: 0A226-0359CK | U96: 0 | V96: 0 | W96: 0 | X96: 0 | Y96: 0 | Z96: 0 | AA96: 0 | AB96: 0 | AC96: 44 | AD96: 0 | AE96: 0 | AF96: 0 | AG96: 0 | AH96: 1 | AI96: 44
A97: 0A226-0360CK | K97: 1 | P97: 1 | S97: 0A226-0360CK | U97: 0 | V97: 0 | W97: 0 | X97: 0 | Y97: 0 | Z97: 0 | AA97: 0 | AB97: 0 | AC97: 44 | AD97: 0 | AE97: 0 | AF97: 0 | AG97: 0 | AH97: 1 | AI97: 44
A98: 0A296-0211 | K98: 1 | N98: 1 | P98: 2 | S98: 0A296-0211 | U98: 0 | V98: 0 | W98: 0 | X98: 0 | Y98: 0 | Z98: 0 | AA98: 0 | AB98: 0 | AC98: 44 | AD98: 0 | AE98: 0 | AF98: 33 | AG98: 0 | AH98: 2 | AI98: 77
A99: 0A296-0215HS | K99: 1 | N99: 1 | P99: 2 | S99: 0A296-0215HS | U99: 0 | V99: 0 | W99: 0 | X99: 0 | Y99: 0 | Z99: 0 | AA99: 0 | AB99: 0 | AC99: 44 | AD99: 0 | AE99: 0 | AF99: 33 | AG99: 0 | AH99: 2 | AI99: 77
A100: 0A296-0216HS | K100: 1 | P100: 1 | S100: 0A296-0216HS | U100: 0 | V100: 0 | W100: 0 | X100: 0 | Y100: 0 | Z100: 0 | AA100: 0 | AB100: 0 | AC100: 44 | AD100: 0 | AE100: 0 | AF100: 0 | AG100: 0 | AH100: 1 | AI100: 44
...
